Workbook
Name dd_attributes: 'PDP Checklist'!$B$15:$O$44

Sheet Table of Contents
B3: Table of Contents | E3: Always use the latest version of this file
B5: =HYPERLINK(VLOOKUP("Section",'PDP Checklist'!A:O,2,FALSE),"PDP Checklist READ ME") -> PDP Checklist READ ME | C5: Product information required for digital health. Utilize this Checklist during NPI to capture digital product information for hand-off to operational resources. | E5: Please provide any feedback on this Checklist, Training, or Process on our Feedback Form!
B6: =HYPERLINK(VLOOKUP("Section",'PDP Checklist'!A:O,2,FALSE),"PDP Checklist") -> PDP Checklist | D6: #'PDP Checklist READ ME'!C5
B8: Learn More & Support | C8: Descriptions, best practices, and additional information for each required product information data/element of the PDP Checklist
B10: Operational Resources | C10: Operational (systems) information, reminders, dependencies, tips & tricks, etc. for each requirement on the checklist, CorpBase entry, and data def job aid instructions.
B12: Data Definition Job Aid | C12: Standardized table of required attributes for a specified product group and type.

Sheet PDP Checklist READ ME
A1: PDP Checklist READ ME
A2: Always use the latest version.
A3: =HYPERLINK(C3,"Why use the PDP Checklist?") -> Why use the PDP Checklist? | C3: #'PDP Checklist READ ME'!C6
A4: =HYPERLINK(C4,"Best in Class PDP") -> Best in Class PDP | C4: #'PDP Checklist READ ME'!C47
A5: =HYPERLINK(C5,"Example of Completed Checklist") -> Example of Completed Checklist | C5: #'PDP Checklist READ ME'!M47
C6: Why use the PDP Checklist? | F6: UPDATE TO THE DATA DEF JOB AID / PDP CHECKLIST
F7: The data def job aid and PDP Checklists have now been combined into one file (this file). Future updates to the the Data Definition job aid tab will automatically update the attributes/properties dynamic table on the PDP Checklist. This will ensure all PMs are using up to date product data recommendations during NPI and data def review. Please be sure to always use the latest version of this file
C8: WHAT is a 'Digital Checklist'? | D8: The Digital Requirements Checklist is a list of product information data & elements that are required for a 'healthy' digital presence on sigmaaldrich.com; the checklist can also be used to capture data for hand-off to operational resources. The requirements represent product data and elements that appear on a product detail page (PDP), within site search, on a category page, etc.
C10: WHO is involved? | D10: PRODUCT MARKETING is responsible for identifying the product data and content to meet the requirements. Product Marketing is the primary audience and expected user group of the Digital Requirements Checklist, responsible for capturing product information and handing over to operational resources for systems updates. OPERATIONAL RESOURCES (e.g. PM Ops, SBS, etc.) are responsible for ensuring product data and content is entered into systems accurately and completely.
C12: WHEN is the checklist used? | D12: The Digital Requirements Checklist should be referenced throughout New Product Introduction (NPI), from ideation to systems set up, so that critical product information can be collected and/or generated in accordance with digital best practices.
C14: WHERE can I find more support? | D14: The 'Learn More & Best Practices' tab provides a description of each element alongside recommended best practices; additional resources, found on EVA, are also provided. Support can also be provided by Digital Category Management, Product Data team, and the Digital Champions Network.
C16: WHY is this so important? | D16: Capturing accurate, complete product information is critical to a PDP's digital health. Launching an NPI with the required product information outlined on the Digital Requirements Checklist will: • Provide product information a customer needs to identify, select & buy a product of interest • Improve product findability within site search • Impact organic search ranking through SEO • Support post-purchase product use • Meet customer expectations of a consistent & intuitive user experience • Better enable scalable acquisition & marketing activities
C19: Best in Class PDP | F19: Example of Completed Checklist:
C20: https://www.sigmaaldrich.com/product/sigma/hpa002891 | F20: Product Info | H20: CorpBase Product Number | I20: =HYPERLINK(VLOOKUP(H20,'Learn More & Support'!$B:$D,2,0),"learn more") -> learn more | J20: New Product Number, must be same as SAP BISMT. Not always = SKU | M20: HPA002891
H21: CorpBase Brand | I21: =HYPERLINK(VLOOKUP(H21,'Learn More & Support'!$B:$D,2,0),"learn more") -> learn more | J21: CorpBase brand, NOT portfolio brand | M21: SIGMA
H22: CorpBase Substance | I22: =HYPERLINK(VLOOKUP(H22,'Learn More & Support'!$B:$D,2,0),"learn more") -> learn more | J22: If applicable; A CB substance shares attributes & search assortment | M22: n/a
H23: Product Group | I23: =HYPERLINK(VLOOKUP(H23,'Learn More & Support'!$B:$D,2,0),"learn more") -> learn more | J23: antibodies | M23: <-- 1. Select Product Group
H24: Product Type | I24: =HYPERLINK(VLOOKUP(H24,'Learn More & Support'!$B:$D,2,0),"learn more") -> learn more | J24: primary monoclonal | M24: <-- 2. Select Product Type
H25: IF PRODUCT GROUP/TYPE DOES NOT EXIST, STOP. CONTACT DCM TO REVIEW DATA DEFINITIONS.
F27: Names | H27: Primary name | I27: =HYPERLINK(VLOOKUP(H27,'Learn More & Support'!$B:$D,2,0),"learn more") -> learn more | J27: Aligns with name in MDGM | M27: Anti-AKT1 antibody produced in rabbit
H28: Name suffix | I28: =HYPERLINK(VLOOKUP(H28,'Learn More & Support'!$B:$D,2,0),"learn more") -> learn more | J28: Auto-populate: Select Attributes & Order below (or enter free text) | M28: Prestige Antibodies® Powered by Atlas Antibodies, affinity isolated antibody, buffered aqueous glycerol solution
H29: Synonyms | I29: =HYPERLINK(VLOOKUP(H29,'Learn More & Support'!$B:$D,2,0),"learn more") -> learn more | J29: Provide at least 1-2 synonyms | M29: Anti-RAC-PK-α antibody produced in rabbit, Anti-Protein kinase B antibody produced in rabbit, Anti-PKB antibody produced in rabbit, Anti-RAC-α serine/threonine-protein kinase antibody produced in rabbit, Anti-C-AKT antibody produced in rabbit
F31: Properties | G31: Suffix Order | H31: Attributes | I31: Priority | J31: Example Product | K31: Example Data | L31: Facet | M31: Attribute Data/Value:
F32: =HYPERLINK(VLOOKUP(H31,'Learn More & Support'!$B:$D,2,0),"learn more") -> learn more | H32: antibody form | I32: Priority 1 | J32: MAB5608 | K32: ascites fluid | L32: Y | M32: affinity isolated antibody
H33: biological source | I33: Priority 1 | J33: MAB5608 | K33: mouse | L33: Y | M33: rabbit
H34: clone | I34: Priority 1 | J34: MAB5608 | K34: GT1b-2b, monoclonal | L34: Y | M34: polyclonal
F35: for more resources: | H35: concentration | I35: Priority 2 | J35: M2320 | K35: ~2 mg/mL | L35: N
F36: Data Def Job Aid | H36: conjugate | I36: Priority 1 | J36: MABF2815 | K36: unconjugated | L36: Y | M36: unconjugated
F37: Fixed Text Picklist | H37: enhanced validation | I37: Priority 2 | J37: AMAB91124 | K37: orthogonal RNAseq | L37: N | M37: orthogonal RNAseq
H38: form | I38: Priority 1 | J38: GR01 | K38: liquid | L38: Y | M38: buffered aqueous glycerol solution
H39: Gene Information | I39: Priority 1 | J39: MAB1687 | K39: human ... VIM(7431) | L39: Y | M39: human ... AKT1(207)
H40: greener alternative category | I40: Priority 3 | J40: 0 | K40: 0 | L40: 0
H41: greener alternative product characteristics | I41: Priority 3 | J41: 0 | K41: 0 | L41: 0
H42: immunogen sequence | I42: Priority 3 | J42: AMAB91124 | K42: LNLSSIILDVNQDRLTQRAIEASNAYSRILQAVQAAEDAAGQALQQADHTWATVVRQGLVDRAQQLLANSTALEEAMLQEQQRLGLVWAAL | L42: N | M42: ERTFHVETPEEREEWTTAIQTVADGLKKQEEEEMDFRSGSPSDNSGAEEMEVSLAKPKHRVTMNEFEYLKLLGKGTFGKVILVKEKATGRYYAMKILKKEVIVA,seq:16,language:1,id:
H43: isotype | I43: Priority 1 | J43: MAB5608 | K43: IgG2b | L43: Y
H44: manufacturer/tradename | I44: Priority 3 | J44: 0 | K44: 0 | L44: 0
H45: mol wt | I45: Priority 1 | J45: M2320 | K45: apparent mol wt 280 kDa | L45: N
H46: NCBI accession no. | I46: Priority 2 | J46: MAB1687 | K46: NM_003380.2 | L46: N
H47: packaging | I47: Priority 3 | J47: AMAB91124 | K47: antibody small pack of 25 μL | L47: Y | M47: antibody small pack of 25 μL
H48: product line | I48: Priority 2 | J48: AMAB91124 | K48: Prestige Antibodies® Powered by Atlas Antibodies | L48: Y | M48: Prestige Antibodies® Powered by Atlas Antibodies
H49: Quality Level | I49: Priority 1 | J49: MAB1687 | K49: 100 | L49: N | M49: 100
H50: recombinant | I50: Priority 3 | J50: 0 | K50: 0 | L50: 0
H51: shipped in | I51: Priority 1 | J51: MAB5608 | K51: dry ice | L51: N | M51: wet ice
H52: species reactivity | I52: Priority 1 | J52: MAB5608 | K52: human, mouse, rat | L52: Y | M52: human
H53: storage temp. | I53: Priority 1 | J53: AMAB91124 | K53: −20°C | L53: N | M53: −20°C
H54: technique(s) | I54: Priority 1 | J54: MAB5608 | K54: immunohistochemistry: suitable | L54: Y | M54: immunohistochemistry: 1:50-1:200 immunofluorescence: 0.25-2 μg/mL
H55: UniProt accession no. | I55: Priority 1 | J55: MAB1687 | K55: P08670 | L55: N | M55: P31749
H56: Web_Antibody_Research_Area_Dim | I56: Priority 1 | J56: 0 | K56: 0 | L56: Y
H61: If you need additional custom attributes not on this list, please insert new rows above this line
F63: Trademarks | H63: Trademarks | I63: =HYPERLINK(VLOOKUP(H63,'Learn More & Support'!$B:$D,2,0),"learn more") -> learn more | J63: If applicable; Check Trademark table to see if value already exists | M63: Prestige Antibodies®
F65: Aliases | H65: UNSPSC Code | I65: =HYPERLINK(VLOOKUP(H65,'Learn More & Support'!$B:$D,2,0),"learn more") -> learn more | J65: Be as specific as possible; look up relevant UNSPSC code | M65: 12352203
F67: Imagery | H67: Product image | I67: =HYPERLINK(VLOOKUP(H67,'Learn More & Support'!$B:$D,2,0),"learn more") -> learn more | J67: File name(s) | M67: HPA0029891ev.jpg; HPA002891ihc.jpg; HPA002891ihc2.jpg; HPA002891f.jpg
H68: Image caption | I68: =HYPERLINK(VLOOKUP(H68,'Learn More & Support'!$B:$D,2,0),"learn more") -> learn more | J68: One per image, specify file name | M68: HPA0029891ev.jpg: Enhanced Validation-Orthogonal RNAseq Confirmation: Immunohistochemistry analysis in human seminal vesicle and skeletal muscle tissues using Anti-AKT1 antibody. Corresponding AKT1 RNA-seq data are presented for the same tissues. HPA002891ihc.jpg: Immunohistochemistry: Immunohistochemical staining of human skeletal muscle shows low expression as expected. HPA002891ihc2.jpg: Immunohistochemistry: Immunohistochemical staining of human seminal vesicle shows high expression. HPA002891f.jpg: Immunofluorescence: Immunofluorescent staining of human cell line A-431 shows localization to nucleoplasm and microtubules
H69: Chemical structure | I69: =HYPERLINK(VLOOKUP(H69,'Learn More & Support'!$B:$D,2,0),"learn more") -> learn more | J69: If applicable. Provide structure (ChemDraw) to structures@merckgroup.com | M69: n/a
F71: Packaging | H71: Pack size (displayed in P&A) | I71: =HYPERLINK(VLOOKUP(H71,'Learn More & Support'!$B:$D,2,0),"learn more") -> learn more | J71: Provide pack size for each material/SKU | M71: 25uL, 100uL
F73: Descriptions | H73: Enter the following prioritized description types at a minimum; additional descriptions can be entered
H74: General Description | I74: =HYPERLINK(VLOOKUP(F73,'Learn More & Support'!$B:$D,2,0),"learn more") -> learn more | J74: Required | M74: AKT1 (v-akt murine thymoma viral oncogene homolog 1) is a Ser/Thr protein kinase, and is also called protein kinase B (PKB). This protein is activated when it is phosphorylated at serine 473 and threonine 308. This gene is localized to human chromosome 14q32.32.
H75: Application | J75: Required | M75: All Prestige Antibodies Powered by Atlas Antibodies are developed and validated by the Human Protein Atlas (HPA) project (www.proteinatlas.org)and as a result, are supported by the most extensive characterization in the industry. The Human Protein Atlas project can be subdivided into three efforts: Human Tissue Atlas, Cancer Atlas, and Human Cell Atlas. The antibodies that have been generated in support of the Tissue and Cancer Atlas projects have been tested by immunohistochemistry against hundreds of normal and disease tissues and through the recent efforts of the Human Cell Atlas project, many have been characterized by immunofluorescence to map the human proteome not only at the tissue level but now at the subcellular level. These images and the collection of this vast data set can be viewed on the Human Protein Atlas (HPA) site by clicking on the Image Gallery link. To view these protocols and other useful information about Prestige Antibodies and the HPA, visit sigma.com/prestige.
H76: Features & Benefits | J76: Required (if applicable) | M76: Prestige Antibodies® are highly characterized and extensively validated antibodies with the added benefit of all available characterization data for each target being accessible via the Human Protein Atlas portal linked just below the product name at the top of this page. The uniqueness and low cross-reactivity of the Prestige Antibodies® to other proteins are due to a thorough selection of antigen regions, affinity purification, and stringent selection. Prestige antigen controls are available for every corresponding Prestige Antibody and can be found in the linkage section. Every Prestige Antibody is tested in the following ways: IHC tissue array of 44 normal human tissues and 20 of the most common cancer type tissues. Protein array of 364 human recombinant protein fragments.
H77: Immunogen | J77: Optional | M77: RAC-α serine/threonine-protein kinase recombinant protein epitope signature tag (PrEST)
H78: Linkage | J78: Optional | M78: Corresponding Antigen APREST70574.
H79: Add'l Product Description #3... | J79: Optional
F81: Documentation | H81: Product documents | I81: =HYPERLINK(VLOOKUP(H81,'Learn More & Support'!$B:$D,2,0),"learn more") -> learn more | J81: List the documents to be uploaded. Include .file extension | M81: Will need a procedure ("Procedure for Fixation, Immunostaining, and Imaging in 384-well Plates")
F83: Peer Reviewed Papers | H83: Citations | I83: =HYPERLINK(VLOOKUP(H83,'Learn More & Support'!$B:$D,2,0),"learn more") -> learn more | J83: Provide as PMIDs | M83: 24737346, 25582346, 16098065, 24797175, 24817011
F85: Related Products | H85: Related products | I85: =HYPERLINK(VLOOKUP(H85,'Learn More & Support'!$B:$D,2,0),"learn more") -> learn more | J85: Enter CorpBase Product number + brand (#### SIGMA) | M85: N/A | N85: See Related Products for F2442 for an example -->
F87: Digital Optimization | H87: Keywords | I87: =HYPERLINK(VLOOKUP(H87,'Learn More & Support'!$B:$D,2,0),"learn more") -> learn more | J87: Not customer-facing | M87: RAC, protein kinase B, PKB
H88: Meta title | I88: =HYPERLINK(VLOOKUP(H88,'Learn More & Support'!$B:$D,2,0),"learn more") -> learn more | J88: ="55-65 characters (Cell will be blue), Count: "&LEN(M88) -> 55-65 characters (Cell will be blue), Count: 26 | M88: Anti-AKT1 antibody, rabbit | N88: Should be between 55-65 characters
H89: Meta description | I89: =HYPERLINK(VLOOKUP(H89,'Learn More & Support'!$B:$D,2,0),"learn more") -> learn more | J89: ="120-156 characters (Cell will be blue), Count: "&LEN(M89) -> 120-156 characters (Cell will be blue), Count: 88 | M89: Prestige Antibodies® Anti-AKT1 antibody produced in rabbit features enhanced validation. | N89: Should be between 120-156 characters
H90: Product Category page | I90: =HYPERLINK(VLOOKUP(H90,'Learn More & Support'!$B:$D,2,0),"learn more") -> learn more | J90: Existing category page title | M90: Fetal Bovine Serum (FBS), Sera
H91: Call to Action | I91: =HYPERLINK(VLOOKUP(H91,'Learn More & Support'!$B:$D,2,0),"learn more") -> learn more | J91: Select 1 "Request a Bulk Order" AND/OR 1 Additional | M91: Request a Bulk Order
H92: Legacy Legal Entity | I92: =HYPERLINK(VLOOKUP(H92,'Learn More & Support'!$B:$D,2,0),"learn more") -> learn more | J92: Default "Merck/Sigma-Aldrich" to enable Product on ALL sites | M92: Merck/Sigma-Aldrich

Sheet PDP Checklist
A1: =HYPERLINK(O1,"Example provided on 'READ ME' tab") -> Example provided on 'READ ME' tab | O1: #'PDP Checklist READ ME'!M46
A2: Section | C2: Product Information Element Click to Learn More | D2: Hidden for dynamic attributes table | E2: Hidden for dynamic attributes table | F2: Hidden for dynamic attributes table | G2: Hidden for dynamic attributes table | H2: Hidden for dynamic attributes table | I2: Quick notes | L2: Hidden for dynamic attributes table | M2: Hidden for dynamic attributes table | N2: Hidden for dynamic attributes table | O2: Input (by Product Marketing) | P2: Copy Input (Column L) to compare data if launching similar products ↓
A3: Product Info | C3: =HYPERLINK(VLOOKUP("CorpBase Product Number",'Learn More & Support'!B:D,2,0),"CorpBase Product Number") -> CorpBase Product Number | I3: New Product Number, must be same as SAP BISMT. Not always = SKU | O3: PMC1108
C4: =HYPERLINK(VLOOKUP("CorpBase Brand",'Learn More & Support'!B:D,2,0),"CorpBase Brand") -> CorpBase Brand | I4: CorpBase brand, NOT portfolio brand | O4: SIAL
C5: =HYPERLINK(VLOOKUP("CorpBase Substance",'Learn More & Support'!B:D,2,0),"CorpBase Substance") -> CorpBase Substance | I5: If applicable; A CB substance shares attributes & search assortment
I6: SELECT PRODUCT GROUP/TYPE. If none apply, contact DCM
C7: =HYPERLINK(VLOOKUP("Product Group",'Learn More & Support'!B:D,2,0),"Product Group") -> Product Group | I7: stable isotopes | O7: <-- 1. Select Product Group
C8: =HYPERLINK(VLOOKUP("Product Type",'Learn More & Support'!B:D,2,0),"Product Type") -> Product Type | I8: various | O8: <-- 2. Select Product Type
A10: Names | C10: Primary name | I10: Aligns with name in MDGM | O10: Methanol-d4
C11: Name suffix | I11: Recommended: Input relevant Attributes & select "Suffix Order" below | O11: ≥99.8% D, ISOM8™
C12: Synonyms | I12: Provide at least 1-2 synonyms | O12: methyl-d3- alcohol d, tetradeuteromethanol
A14: Properties | B14: Suffix Order | C14: Attributes | D14: Priority - change to number | E14: Priority | I14: Example Product | J14: Example Data | K14: Facet | O14: Attribute Data/Value:
A15: =HYPERLINK(VLOOKUP(C14,'Learn More & Support'!$B:$D,2,0),"learn more") -> learn more | C15: {=IFERROR( IF($I$7="_discontinued","Select Product Group & Product Type",_xlfn._xlws.FILTER(LOGIC!K:V,LOGIC!H:H=$I$7&IF($I$8=0,"",$I$8))),"Enter valid Product Group AND Product Type")} -> assay | D15: Facet driving attribute | E15: Priority 1 | F15: ProductAttributes | G15: ATTRIBUTE TYPE: Assay | H15: 0 | I15: 151866 | J15: ≥99% (CP) | K15: Y | L15: Purity | M15: 0 | N15: 0 | O15: ≥99% (CP)
B16: 1 | C16: form | D16: Facet driving attribute | E16: Priority 1 | F16: ProductAttributes | G16: ATTRIBUTE TYPE: Physical Form | H16: 0 | I16: 151866 | J16: liquid | K16: Y | L16: Physical Form | M16: 0 | N16: 0 | O16: liquid
A17: additional resources: | C17: grade | D17: Facet driving attribute | E17: Priority 1 | F17: ProductAttributes | G17: ATTRIBUTE TYPE: Special Grade and web special grade | H17: web special grade is facetable; but web special grade does not show on the PDP; special grade is the opposite | I17: 154784 | J17: spectrophotometric grade | K17: Y | L17: grade | M17: 0 | N17: 0 | O17: reagent grade
A18: Fixed Text Picklist | B18: 3 | C18: isotopic purity | D18: Facet driving attribute | E18: Priority 1 | F18: ProductAttributes | G18: ATTRIBUTE TYPE: Isotopic Purity | H18: 0 | I18: 151866 | J18: ≥99.6 atom % D | K18: Y | L18: Isotope | M18: 0 | N18: 0 | O18: ≥99.8 atom % D
C19: mass shift | D19: Facet driving attribute | E19: Priority 1 | F19: ProductAttributes | G19: ATTRIBUTE TYPE: Mass Shift | H19: 0 | I19: 151866 | J19: M+12 | K19: Y | L19: mass shift | M19: 0 | N19: 0 | O19: M+4
C20: technique(s) | D20: Facet driving attribute | E20: Priority 1 | F20: ProductAttributes | G20: ATTRIBUTE TYPE: Titertest | H20: use the drop down in "METHOD" | I20: 151866 | J20: NMR: suitable | K20: Y | L20: Technique | M20: method | N20: method
C21: bp | D21: High priority attribute | E21: Priority 2 | F21: ProductAttributes | G21: ATTRIBUTE TYPE: Boiling Point | H21: 0 | I21: 151866 | J21: 80.7 °C (lit.) | K21: Y | L21: boiling point | M21: 0 | N21: 0 | O21: 65.4 °C (lit)
C22: concentration | D22: High priority attribute | E22: Priority 2 | F22: ProductAttributes | G22: ATTRIBUTE TYPE: Concentration | H22: 0 | I22: 176680 | J22: 50 wt. % in D2O | K22: N | L22: 0 | M22: 0 | N22: 0
C23: density | D23: High priority attribute | E23: Priority 2 | F23: ProductAttributes | G23: ATTRIBUTE TYPE: Density | H23: 0 | I23: 151866 | J23: 0.893 g/mL at 25 °C (lit.) | K23: N | L23: 0 | M23: 0 | N23: 0 | O23: 0.888 g/mL at 25 °C (lit.)
C24: impurities | D24: High priority attribute | E24: Priority 2 | F24: ProductAttributes | G24: ATTRIBUTE TYPE: Impurities | H24: 0 | I24: 151793 | J24: ≤0.0500% water | K24: N | L24: 0 | M24: 0 | N24: 0 | O24: <0.5% water
C25: InChI | D25: High priority attribute | E25: Priority 2 | F25: Aliases | G25: drop down type: InChl | H25: must be on the substance level | I25: 151866 | J25: 1S/C6H12/c1-2-4-6-5-3-1/h1-6H2/i1D2,2D2,3D2,4D2,5D2,6D2 | K25: N | L25: 0 | M25: 0 | N25: 0 | O25: 1S/CH4O/c1-2/h2H,1H3/i1D3,2D
C26: InChI key | D26: High priority attribute | E26: Priority 2 | F26: Aliases | G26: drop down type: InChl key | H26: must be on the substance level | I26: 151866 | J26: XDTMQSROBMDMFD-LBTWDOQPSA-N | K26: N | L26: 0 | M26: 0 | N26: 0 | O26: OKKJLVBELUTLKV-MZCSYVLQSA-N
C27: mp | D27: High priority attribute | E27: Priority 2 | F27: ProductAttributes | G27: ATTRIBUTE TYPE: Melting Point | H27: 0 | I27: 151866 | J27: 6.5 °C (lit.) | K27: Y | L27: mp | M27: 0 | N27: 0
C28: packaging | D28: High priority attribute | E28: Priority 2 | F28: ProductAttributes | G28: ATTRIBUTE TYPE: Packaging quantity | H28: facet only on pack_id (was NEVER used on the red site - utility is dubious) | I28: 151793 | J28: glass bottle of 25 g, 50 g | K28: Y | L28: packaging | M28: pack_id | N28: pack_id | O28: glass bottle of 1g, 5g
C29: refractive index | D29: High priority attribute | E29: Priority 2 | F29: ProductAttributes | G29: ATTRIBUTE TYPE: Refractive Index | H29: 0 | I29: 151866 | J29: n20/D 1.421 (lit.) | K29: N | L29: 0 | M29: 0 | N29: 0 | O29: n20/D 1.326 (lit.)
C30: SMILES string | D30: High priority attribute | E30: Priority 2 | F30: Aliases | G30: drop down type: SMILES | H30: must be on the substance level; 30 characters or less; if more than 30 characters, raise a JIRA for CorpBase Helpdesk | I30: 151866 | J30: [2H]C1([2H])C([2H])([2H])C([2H])([2H])C([2H])([2H])C([2H])([2H])C1([2H])[2H] | K30: N | L30: 0 | M30: 0 | N30: 0 | O30: [2H]OC([2H])([2H])[2H]
C31: storage temp. | D31: High priority attribute | E31: Priority 2 | F31: ProductAttributes | G31: ATTRIBUTE TYPE: Storage Temp | H31: 0 | I31: 1.03643 | J31: 2-30°C | K31: N | L31: 0 | M31: 0 | N31: 0
C32: autoignition temp. | D32: Low priority attribute | E32: Priority 3 | F32: ProductAttributes | G32: ATTRIBUTE TYPE: Autoignition temp | H32: must be on the substance level | I32: 1.03643 | J32: 573 °F | K32: N | L32: 0 | M32: 0 | N32: 0
C33: contains | D33: Low priority attribute | E33: Priority 3 | F33: ProductAttributes | G33: ATTRIBUTE TYPE: Additive | H33: 0 | I33: 176036 | J33: copper as stabilizer | K33: N | L33: 0 | M33: 0 | N33: 0
C34: expl. lim. | D34: Low priority attribute | E34: Priority 3 | F34: ProductAttributes | G34: ATTRIBUTE TYPE: Explosion limit | H34: 0 | I34: 151866 | J34: 0.34-6.3 % (lit.) | K34: N | L34: 0 | M34: 0 | N34: 0
C35: vapor density | D35: Low priority attribute | E35: Priority 3 | F35: ProductAttributes | G35: ATTRIBUTE TYPE: Vapor density vs air | H35: 0 | I35: 151793 | J35: 2 (vs air) | K35: N | L35: 0 | M35: 0 | N35: 0
C36: vapor pressure | D36: Low priority attribute | E36: Priority 3 | F36: ProductAttributes | G36: ATTRIBUTE TYPE: Vapor pressure | H36: 0 | I36: 151793 | J36: 3.67 psi ( 20 °C) | K36: N | L36: 0 | M36: 0 | N36: 0
C38: evapn. residue
B39: 2 | C39: product line | O39: ISOM8™
C40: product line
C41: product type | O41: stable isotopes
C44: If you need additional custom attributes not on this list, please insert new rows above this line
A46: Trademarks | C46: Trademarks | I46: If applicable; Check Trademark table to see if value already exists | O46: [TM="ISOM8"]
A48: Aliases | C48: UNSPSC Code | I48: Be as specific as possible; look up relevant UNSPSC code | O48: 12352104
A50: Imagery | C50: Product image | I50: File name(s)
C51: Image caption | I51: One per image, specify file name
C52: Chemical structure | I52: If applicable. Provide structure (ChemDraw) to structures@merckgroup.com
A54: Packaging | C54: Pack size (displayed in P&A) | I54: Provide pack size for each material/SKU | O54: 1g in glass bottle, 5g in glass bottle
A56: Descriptions | C56: General Description | I56: Required | O56: "Welcome to our [TM=""ISOM8""] line of high-quality products available and able to scale for manufacturing. Within our ISOM8 team, we have expertise and documentation to support ISO 9001, non-GMP, industrial needs, as defined by our <a href=""https://www.sigmaaldrich.com/US/en/life-science/quality-and-regulatory-management/m-clarity-program"">[TM=""M-Clarity""] Program</a>. Our portfolio of ISOM8 products and chemistries is ever evolving to support our valued [TM=""Sigma-Aldrich""] customers' requirements. Please navigate to our documents section to look at dossiers and other quality documentation for this product, provided with support of our <a href=""https://www.sigmaaldrich.com/US/en/services/product-services/elevate-quality-program"">Elevate Program</a>. <br><br> Our [TM=""ISOM8""] deuterated methanol is available internationally in both prepack sizes and configurable bulk packaging.
A57: Enter the following prioritized description types at a minimum; additional descriptions can be entered | C57: Application | I57: Required | O57: <<b>Chemical Synthesis</b> Deuterated methanol acts as a key building block to incorporate deuterium into larger molecules, either directly or through transformation.
C58: Features & Benefits | I58: Required (if applicable)
C59: Packaging | I59: Optional | O59: 1g and 5g containers packaged in glass bottles.<br> For bulk amounts in US, we offer configurable quantities packaged based upon your specific needs.
C60: Legal information | O60: ISOM8 is a trademark of Sigma-Aldrich Co. LLC
C61: Add'l Product Description #3... | I61: Optional
A63: Documentation | C63: Product documents | I63: List the documents to be uploaded. Include .file extension
A65: Peer Reviewed Papers | C65: Citations | I65: Provide as PMIDs
A67: Related Products | C67: Related products | I67: Enter CorpBase Product number + brand (#### SIGMA)
A69: Digital Optimization | C69: Keywords | I69: Names/Synonyms that are NOT customer-facing | O69: dimetilsulfoxido, 276855
C70: Meta title | I70: ="55-65 characters (Cell will turn green), Count: "&LEN($O$70) -> 55-65 characters (Cell will turn green), Count: 63 | O70: Dimethyl sulfoxide (DMSO) ≥99.9%, ISOM8™, anhydrous (extra dry)
C71: Meta description | I71: ="120-156 characters (Cell will turn green), Count: "&LEN($O$71) -> 120-156 characters (Cell will turn green), Count: 100 | O71: DMSO anhydrous (extra dry) to support ISO 9001, non-GMP, industrial production. Buy, Rate, & Review!
C72: Product Category page | I72: Existing category page title
C73: Call to Action | I73: Select 1 "Request a Bulk Order" AND/OR 1 Additional | O73: Request a Bulk Order
C74: Legacy Legal Entity | I74: Default "Merck/Sigma-Aldrich" to enable Product on ALL sites | O74: Sigma-Aldrich

Sheet Learn More & Support
A1: Section | B1: Required element / *required if applicable | C1: Hyperlink Formula (hide) | D1: Description/Definition | E1: Best Practice | F1: More Information | G1: Who can I reach out to for Support?
A2: Product Structure | B2: CorpBase Product Number | C2: #'Learn More & Support'!B2 | D2: The Corpbase product number appears in the header of the product detail page (PDP) as well as in the page URL. This number is not the full SAP material (SKU) number (e.g. XXXX-25MG), but rather is the 'base' product number, which is captured in SAP as the 'old material number' (BISMT). | E2: CorpBase product number should match the SAP BISMT in PRD, PRE, and PRP; Ensure that the BISMT/brand combination is unique and available in Corpbase | F2: Product Numbers (EVA) | G2: DCM (Consultation)
A3: Product Structure | B3: CorpBase Brand | C3: #'Learn More & Support'!B3 | D3: The CorpBase brand is not the Portfolio Brand; rather, it is a value that aligns with SAP master data. The CorpBase brand appears in the PDP URL. | E3: CorpBase brand should match SAP PRD/PRE Division (SPART) and PRP (Brand_ID); Ensure that the BISMT/brand combination is unique and available in Corpbase | F3: CorpBase and Portfolio Brands (EVA) | G3: DCM (Consultation)
A4: Product Structure | B4: CorpBase Substance | C4: #'Learn More & Support'!B4 | D4: To group similar products under the same primary name. | E4: Use a substance when all products share intrinsic properties, like a primary name or a unique identifier (e.g. CAS number), or when products should be "rolled up" in site search results. | F4: Substance & Product Level (EVA) | G4: DCM (Consultation)
A5: Product Structure | B5: Product Group | C5: #'Learn More & Support'!B5 | D5: Select a Product Group from the Data Definition Job Aid | E5: In the job aid, 1) filter results for the product group and product type of the NPI, 2) select the Properties (attributes) listed as required, 3) paste the Properties into column B of this checklist, then 4) enter product-specific values in Input column | F5: Data Definition (EVA) | G5: DCM (Consultation)
A6: Product Structure | B6: Product Type | C6: #'Learn More & Support'!B6 | D6: The Product Type attribute captures data describing "what it is" for a product and is associated with the product categorization/data definition group. This data is displayed in the 'Product Category' facet (filter) on site search results and on category pages, allowing a customer to refine a set of search results by the type of product they are interested in. | E6: A product type value should describe "what it is", without being so specific or narrow that other products are excluded. Examples: syringe filter, antibody, culture media, solvent, etc. Reference the existing list of product type values when identifying the product type; if a value does not exist, consult Digital Category Management for assistance. | F6: Data Definition (EVA) | G6: DCM (Consultation)
A7: Names | B7: Primary name | C7: #'Learn More & Support'!B7 | D7: A product's primary name appears as the H1 on the product detail page, as the primary designator on site search results and on category pages, and is printed on labels generated from SAP. This name should align with the product name in MDGM. | E7: The primary name should be created with consideration of customer language and search behavior. If a product is added to an existing substance, it will inherit a name automatically. | F7: Product Name and Suffix (EVA) | G7: SBS review (quality check)
A8: Names | B8: Name suffix | C8: #'Learn More & Support'!B8 | D8: A product name suffix is a sub-heading (H2) of the primary product name. A relevant name suffix is an important SEO element, contributes to findability in site search (displays as 'Description' in main site search and is concatenated with the primary name in category page product tables) and allows customers to differentiate between products with the same primary name. | E8: To maintain data continuity, a name suffix should be "built" from attribute data designated in the product data definition (see 'Attributes' section below). Note that the name suffix will print on labels for products manufactured/packaged out of SAP. For custom name suffixes, enter free text (which will be loaded as ID_Clarifier) | F8: Product Name and Suffix (EVA) | G8: SBS review (quality check)
A9: Names | B9: Synonyms | C9: #'Learn More & Support'!B9 | D9: Synonyms are additional names, beyond the primary product name, that the product may be known as. Synonyms are an important SEO element and impact the relevancy of site search results. | E9: A product should have a minimum of 1-2 synonyms that represent what a customer would call the product, not parsed data (e.g. a synonym for Anti-NFE2L2 antibody should be 'Anti-NRF2', not 'NRF2'). Synonyms should represent customer language - what customers call the product; synonyms can be identified from search data, VOC, literature, vendor-provided information, etc. | F9: Product Name and Suffix (EVA) | G9: SBS assistance
A10: Names | B10: Trademarks | C10: #'Learn More & Support'!B10 | D10: Trademarks may appear in product data, including a product's primary name, name suffix, description, etc.; trademarks must be esablished in CorpBase in order to be used in product data. | F10: Trademarks (EVA) | G10: DCM (Consultation)
A11: Aliases | B11: UNSPSC code | C11: #'Learn More & Support'!B11 | D11: United Nations Standard Products and Services Code (UNSPSC) is a 4-5 level taxonomy of products and services for use in eCommerce. This categorization code is critical for B2B customers; products missing these data may be removed from B2B catalogs or downgraded in B2B search results | E11: Assign a code that is as specific as possible (in the lower levels of the taxonomy). https://www.ungm.org/Public/UNSPSC https://www.unspsc.org/library | F11: Aliases (EVA) | G11: SBS assistance
A12: Imagery | B12: Product Image | C12: #'Learn More & Support'!B12 | D12: Relevant product imagery is important product information that helps a customer to identify & select a product of interest, set expectations for what will be received upon order, and for post-purchase product use. The image displays on the PDP; if a product image is not provided, the space is filled with a generic vibrant M. | E12: Imagery best practices, including imagery standards, what makes a good image, image specifications, etc. are described in depth on EVA. A PDP may contain multiple images; display order (sequence) must be defined if multiple images are submitted for a given product. | F12: Images (EVA) | G12: SBS assistance
A13: Imagery | B13: Image caption | C13: #'Learn More & Support'!B13 | D13: Captions are text descriptions of images. Captions provide more information for a product image and are important for accessibility. | E13: Image caption should be relevant, descriptive, and provide additional supporting information. If the same image is being used for multiple products, ensure the caption is applicable to all products. | F13: Images (EVA) | G13: SBS review (quality check)
A14: Imagery | B14: Image alt text | C14: #'Learn More & Support'!B14 | D14: Alt text (alternative text) is a text replacement for an image; used to explain what the image is and what the image is trying to convey to the user. It is important for accessibility, as it displays in place of an image on a webpage if the image fails to load on a user's screen. It is also an important SEO element. | E14: Image alt text should be descriptive and specific, containing details that provide a customer context to the image's topic and help the customer to understand what the image is and why is it relevant to the webpage. Alt text should be less than 125 characters. | F14: Images (EVA)
A15: Imagery | B15: Chemical structure | C15: #'Learn More & Support'!B15 | E15: If applicable. Provide the structure (ChemDraw) to structures@merckgroup.com during NPI | G15: PM Only
A16: Packaging | B16: Pack size (displayed in P&A) | C16: #'Learn More & Support'!B16 | D16: Pack size information displays in the Pricing & Availability clip; gives a quick view of the quantity of product for a given SKU size. | E16: Pack size should represent the total quantity of the material, not the full packaging specs (e.g. "25uL", not "25uL in an amber vial") | F16: Pack size data (EVA) | G16: PM Only
A17: Properties | B17: Attributes | C17: #'Learn More & Support'!B17 | D17: Attributes are characteristics of a product that are captured as structured data in CorpBase and displayed on PDPs as "Properties". Attributes captured for a new product should represent the information that a customer needs to identify, select, order, or use a product, and should consistently be captured across a product group (product category or product type). The set of required attributes for a product group is known as 'data definition'. Attribute data, structured precisely in Corpbase, also drives facets that display on site search results and category pages. This is another reason why complete, standardized attribute data is critical. | E17: Reference the 'NPI Data Definition Process' tab for a full workflow and RACI. Reference the 'Data Definition Job Aid' for required attributes by product group. A new product should first be categorized (identify the product group/type of the product) before the required attributes can be identified. Once categorized, use the Merchandising Scorecard and the Data Definition Job Aid, which document existing data definitions, to identify the web product data that is needed. For each required attribute, provide accurate, customer-facing data, referencing the existing list of attribute values ('picklist values') to ensure that data structure is maintained. If a product group, data definition, or picklist value does not exist, consult Digital Category Management for assistance. | F17: Data Definition (Confluence) | G17: DCM/SBS support (data mining, gap filling, etc)
A18: Descriptions | B18: Descriptions | C18: #'Learn More & Support'!B18 | D18: Description text appears in the "Descriptions" section of the PDP and provides additional product information to customers for use in product selection and post-purchase use. Descriptions are also important SEO elements. There are many different description types, which appear as sub-headings on the PDP; all descriptions are free-text fields. | F18: Descriptions (EVA) | G18: SBS assistance (data mining/proposal with PM approval)
A19: Documentation | B19: Product documents | C19: #'Learn More & Support'!B19 | D19: Product technical and marketing documents provide supporting product information that can assist a customer in product selection and use. Technical documents include user guides, product information sheets, data sheets, and technical bulletins, etc. Marketing documents include flyers, brochures, gated content, etc. Technical and marketing documents are maintained in the digital asset management (DAM) system; this excludes safety and quality documents (e.g. SDS, CoA, CoO). | F19: Documentation Overview (EVA) | G19: PM Only
A20: Peer Reviewed Papers | B20: Citations | C20: #'Learn More & Support'!B20 | D20: Citing peer reviewed publications that use a product can provide a social proof point to customers as well as providing additional content about the product's use. | E20: Citations should be relevant to the product and provided as PMID numbers. | F20: Citations and peer reviewed papers (EVA) | G20: SBS assistance
A21: Related Products | B21: Related products | C21: #'Learn More & Support'!B21 | D21: A curated list of related products can provide customers insight into additional relevant products, such as products that are "required but not included", accessories or consumables, replacements or recommended products, etc. | E21: Indicate the relationship of products (e.g. "recommended with", "for use with", etc.) and the directionality of the relationship (e.g. product X is related to product Y unidirectionally, or product X and product Y are related to each other bidirectionally). There is a Maximum number of related products allowed. | F21: Related Products (EVA) | G21: PM Only (SBS can review post launch)
A22: Digital Optimization | B22: Keywords | C22: #'Learn More & Support'!B22 | D22: Keywords contribute to relevancy of site search results, but they do not publish on the PDP (are not customer-facing). | E22: Keywords should be relevant to the product and represent words or terms that a customer might search when looking for the product. Do not include keywords that would result in a customer seeing irrelevant or erroneous products in a search. | G22: SBS review (quality check)
A23: Digital Optimization | B23: Meta title | C23: #'Learn More & Support'!B23 | D23: Meta title (title tag) is text that displays in external search engine (e.g. Google) results and browser tabs for a webpage. A custom meta title offers an opportunity to provide more relevant information/positioning to customers and is an important SEO element. | E23: Existing PDP data (e.g. primary name, CAS #, etc.) is used when custom meta title has not been captured. When crafting a custom meta title, include keywords identified from search data to reflect the words and behaviors of customers. Custom meta titles should be 55-65 characters long and include the core keyword​. Must be unique (do not duplicate on other pages) | G23: SBS review (quality check)
A24: Digital Optimization | B24: Meta description | C24: #'Learn More & Support'!B24 | D24: Meta description is the brief summary text that displays in external search engine (e.g. Google) results for a webpage. The text should give a customer an idea of the content that is on the page. Meta description is an important SEO element. | E24: Existing PDP data is used when custom meta description has not been captured. When crafting a custom meta description, it should be <200 characters long and use relevant keywords. Ensure that it aligns with on-page content. Summarize and accurately describe the content the user will find on the page and provide motivation to read it (a CTA – Call To Action)​. Must be unique (do not duplicate on other pages) | G24: SBS review (quality check)
A25: Digital Optimization | B25: Product Category page | C25: #'Learn More & Support'!B25 | D25: Products may be included on Product Category Pages, which present a key group of related products and supporting content to allow customers to compare, select & order products of interest. | E25: Product Category Pages are not a comprehensive product taxonomy, so not all products will appear on a category page. Products should be added to existing category pages only when relevant; discussion with all impacted business stakeholders should precede product addition. New category page requests must go through Marcom. | F25: Product Category (EVA) | G25: SBS review (quality check)
A26: Digital Optimization | B26: Call to Action | C26: #'Learn More & Support'!B26 | D26: Call to Actions (CTAs) are buttons on the P&A clip which direct the customer to a sigmaaldrich.com lead generation form. The CTA information is stored in CorpBase. | E26: A given PDP can have one “Request a Bulk Order” CTA, and one additional non-Bulk CTA for a maximum of two CTAs. If you do not want a “Request a Bulk Order” CTA, you can have a maximum of one CTA. See EVA page for full list of options, and instructions on how to fill out the template and work with DCM to load. | F26: Call to Action (CTAs) Button (EVA) | G26: PM Only
A27: Digital Optimization | B27: Legacy Legal Entity | C27: #'Learn More & Support'!B27 | D27: This field should be reviewed depending on if you want a product to be available on the sigmaaldrich.com AND/OR sigmaaldrich.cn (China only) & other consolidated websites. For example, if the value is left blank, it is going to default to "Sigma-Aldrich" (showing in the SIAL.com and not .cn (China only). For NPI, make sure it’s Sigma-Aldrich or Merck/Sigma-Aldrich; unless you are directed otherwise for Blue China BoR only, then it’s Merck. Unless there is a specific reason not to sell in China, our suggestion is to use Merck/Sigma-Aldrich. If there are any compliance or sales blocks those will be put in place to prevent these products from being sold on sigmaaldrich.cn. | E27: Please use Merck/Sigma-Aldrich unless directly otherwise. | G27: DCM

Sheet Operational Resources
A1: Operations READ ME | B1: Header Locations
A2: Always use the latest version. | D2: Why use the Data Def Job Aid? | G2: How to use data from PDP Checklist | N2: How to do CorpBase pre-check? | S2: Product data on product labels | W2: YYD_LSIND must match CorpBase product number; YYD_LSWEB must match CorpBase BRAND | AF2: CB Synonym Web Display (and Meta Description JIRA requests) | AJ2: Data Def Workflow | BF2: Call to Action Button Options | BH2: Helpful Links
A3: =HYPERLINK(B3,"Why use the Data Def Job Aid") -> Why use the Data Def Job Aid | B3: #'Operational Resources'!D2 | D3: WHAT is the Data Definition job aid? | E3: The Data Definition job aid outlines the required attribute data (data definition schema) for different product groups. | G3: Section | H3: Product Information Element | I3: More Info & Best Practices | J3: Quick Notes for Operations | K3: How to Implement (Responsible/Accountable: NPI Ops, PM Ops, SBS, etc.) | L3: Watch-outs & Best practices | N3: Method 1: PIM client | O3: https://pim.milliporesigma.io/ | S3: Labels. CorpBase feeds some data to labels such as name, name suffix, CAS number, linear chemical formula, hill notation, Enzyme Commission number, | W3: CorpBase BRAND_ID | X3: CorpBase BRAND_TEXT | Y3: CorpBase BRAND_SHORT | Z3: CorpBase BRAND_DISPLAY | AA3: Notes | AB3: PRD Division (SPART) | AC3: PRE Division (SPART) | AD3: PRP Brand_ID | BF3: Request a Bulk Order | BH3: Product Data EVA Room
A4: =HYPERLINK(B4,"How to use data from PDP Checklist") -> How to use data from PDP Checklist | B4: #'Operational Resources'!G2 | G4: Product Info | H4: =HYPERLINK(VLOOKUP("CorpBase Product Number",'Learn More & Support'!B:D,2,0),"CorpBase Product Number") -> CorpBase Product Number | I4: =HYPERLINK(VLOOKUP(H4,'Learn More & Support'!B:D,2,0),"learn more") -> learn more | J4: SAP BISMT must match CorpBase Product Number; 1 BISMT can have many SKUs on the same PDP page | K4: Batchloader / CorpBase Client | L4: Product must be created in SAP (can be done in parallel). CorpBase product number (and SAP BISMT) should NOT be SKU-specific. Confirm with PM if they enter a SKU as a Product Number, instead of creating one Product Number, with multiple SKUs that share data. | O4: Enter the CorpBase product number (a.k.a. old material number, BISMT) into the PIM | S4: Color Index Number, chemical name synonyms, storage temperature, molecular weight, molecular weight (Daltons) melting point, boiling point, density, | W4: 20 | X4: SIAL | Y4: 1 | Z4: Sigma-Aldrich | AB4: 12, 14 | AC4: 12, 14 | AD4: SA | BF4: =$BF$3&" & "&BF7 -> Request a Bulk Order & Request more information | BH4: Digital Category Management EVA room
A5: =HYPERLINK(B5,"Pre-Check") -> Pre-Check | B5: #'Operational Resources'!N2 | D5: WHO is involved? | E5: PRODUCT MANAGERS can use the job aid to identify/provide the attributes required (columns A-E) during NPI or product data enhancement/clean-up. | O5: If nothing returns, then the product number is available to use. | S5: refractive index, vapor pressure | W5: 22 | X5: VETEC | Y5: V | Z5: Vetec | AB5: V4, V8 | AC5: V4, V8 | AD5: VT | BF5: =$BF$3&" & "&BF8 -> Request a Bulk Order & Request a Sample | BH5: Data Definition Job Aid in Confluence
A6: =HYPERLINK(B6,"Product data on product labels") -> Product data on product labels | B6: #'Operational Resources'!S2 | E6: OPERATIONAL RESOURCES can use the job aid (columns F-H) to understand how to enter data in the correct Corpbase location. | W6: 21 | X6: SAJ | Y6: J | Z6: SAJ | AB6: J8 | AC6: J8 | BF6: =$BF$3&" & "&BF9 -> Request a Bulk Order & Request a Demo | BH6: CorpBase Training Videos
A7: =HYPERLINK(B7,"Brand Match") -> Brand Match | B7: #'Operational Resources'!W2 | S7: This data feeds into an SAP table called ZEHS_MKT_ATTRIB every day through a cron job at 2 AM CST. Products that are marked “Not Ready” will not have | W7: 50 | X7: USP | Y7: X | Z7: USP | AB7: X2 | AC7: X2 | AD7: US | BF7: Request more information | BH7: DCM scorecard
A8: =HYPERLINK(B8,"CB Synonym Web Display") -> CB Synonym Web Display | B8: #'Operational Resources'!AF2 | D8: WHERE can I find what I'm looking for? | E8: Column A-->E: Data Definition Schemas established by the DCM team | H8: =HYPERLINK(VLOOKUP("CorpBase Brand",'Learn More & Support'!B:D,2,0),"CorpBase Brand") -> CorpBase Brand | I8: =HYPERLINK(VLOOKUP(H8,'Learn More & Support'!$B:$D,2,0),"learn more") -> learn more | J8: SAP Brand must match CorpBase Brand: PRD/PRE Division (SPART); PRP Brand (BRAND_ID) | K8: Batchloader / CorpBase Client | L8: Product must be created in SAP (can be done in parallel) | S8: data flow into this table and if there is a brand mismatch between this table and CorpBase, updates will not happen either. | W8: 23 | X8: ROCHE | Y8: K | Z8: Roche | AB8: K5 | AC8: K5 | AD8: RO | BF8: Request a Sample
A9: =HYPERLINK(B9,"Data Def Workflow") -> Data Def Workflow | B9: #'Operational Resources'!AJ2 | E9: Column F-->H: How to enter the product data using the CorpBase batchloader | H9: CorpBase Substance | I9: =HYPERLINK(VLOOKUP(H9,'Learn More & Support'!$B:$D,2,0),"learn more") -> learn more | J9: To group similar products in a substance, they must share the same primary name; new products can be assigned into new or existing substances | K9: Batchloader / CorpBase Client | N9: Method 2: CorpBase | O9: Open the batchloader: https://go.sial.com/Citrix/1912CU1PRODWeb/ | W9: 24 | X9: PM | Y9: P | Z9: Performance Materials | AB9: A2, A4 | AC9: A2, A4 | BF9: Request a Demo | BH9: Batchflow
A10: =HYPERLINK(B10,"Call to Action Button Options") -> Call to Action Button Options | B10: #'Operational Resources'!BF2 | E10: Column I-->J: Example product number and data | H10: Product Group | I10: =HYPERLINK(VLOOKUP(H10,'Learn More & Support'!$B:$D,2,0),"learn more") -> learn more | J10: ='PDP Checklist'!I7 -> stable isotopes | K10: Batchloader / CorpBase Client | L10: During batchloader request to Product Data, indicate selected Product Group | N10: batchloader (Report) | O10: Download the latest version | S10: The product data team can assist with changing data that touches the label but if it outside of that it is not our responsibility. | W10: 9 | X10: Obsolete | Y10: 9 | Z10: Genosys | AA10: Not available in BatchLoader | BH10: NPDI
A11: =HYPERLINK(B11,"Helpful Links") -> Helpful Links | B11: #'Operational Resources'!BH2 | E11: Coumn K-->N: facet related data fields | H11: Product Type | I11: =HYPERLINK(VLOOKUP(H11,'Learn More & Support'!$B:$D,2,0),"learn more") -> learn more | J11: ='PDP Checklist'!I8 -> various | K11: Batchloader / CorpBase Client | L11: During batchloader request to Product Data, indicate selected Product Type | O11: Open the batchloader in Citrix; go to the CorpBase tab; Drop down and select Report | S11: We cannot trouble shoot the SAP tables or templates. | W11: 60 | X11: SIGALD | Y11: Q | Z11: Sigma-Aldrich | AB11: Q4, Q8 | AC11: Q4, Q8 | AD11: SG | BH11: BPM
G12: IF PRODUCT GROUP/TYPE DOES NOT EXIST, STOP. CONTACT DCM TO REVIEW DATA DEFINITIONS. | L12: Confirm PM has used Data Definition job aid and/or worked with Digital Category Management or Product Data | O12: Enter CorpBase product number and brand; Select Primary Name; click Get Report | W12: 70 | X12: HONEYWELL | Y12: H | Z12: Honeywell | AA12: Not available in BatchLoader | AB12: H9 | AC12: H9 | AD12: HW | BH12: Static Content/Blue PDP STEP/Page Edits
D13: WHEN is the job aid used? | E13: During NPI and product data enhancement (clean-up), to identify the required attributes and to ensure data is correctly added to systems. | O13: If nothing shows up under Primary Name, then the product number and brand combo can be used. | S13: The following table was provided by SAP IT (Pradeep) for all fields that can possibly be included on a label. | W13: 80 | X13: BANDJ | Y13: B | Z13: Burdick & Jackson | AA13: Not available in BatchLoader
O14: This function can be done in batch for a list of CorpBase product numbers. | S14: Assay | T14: Enzyme Commision number | U14: Name Suffix | W14: 81 | X14: AVANTI | Y14: T | Z14: Avanti | AB14: T2 | AC14: T2 | AD14: AV | BH14: How to request a new Trademark addition to CorpBase?
D15: WHY is this so important? | E15: The job aid will help to ensure that products appear on the web with a complete & standardized set of product data, | G15: Names | H15: Primary name | I15: =HYPERLINK(VLOOKUP(H15,'Learn More & Support'!$B:$D,2,0),"learn more") -> learn more | J15: CorpBase primary name should match ERP and MDGM product name | K15: Batchloader / CorpBase Client | L15: Primary Name Flag should be marked for the chosen name | S15: Boiling point | T15: Hill notation of chemical formula | U15: Primary Name | W15: 1 | X15: SIGMA | Y15: S | Z15: Sigma | AB15: S2, S4, S8 | AC15: S2, S4, S8 | AD15: SI | BH15: CorpBase HelpDesk and CorpBase Graphics
E16: which will improve product findability (surfacing products in search, enabling facets), present relevant data on a PDP, drive SEO, etc. | H16: Name suffix | I16: =HYPERLINK(VLOOKUP(H16,'Learn More & Support'!$B:$D,2,0),"learn more") -> learn more | J16: Emphasize use of existing Attributes & Order (see below) in CB over free text/ID clarifier | K16: Batchloader / CorpBase Client | L16: Emphasize that it is not best practice to use ID clarifier for name suffix | S16: CAS number | T16: Linear chemical formula | U16: Product storage temperature | W16: 2 | X16: ALDRICH | Y16: A | Z16: Aldrich | AB16: A2, A4 | AC16: A2, A4 | AD16: AL | BH16: CorpBase Graphics Object Load Template
H17: Synonyms | I17: =HYPERLINK(VLOOKUP(H17,'Learn More & Support'!$B:$D,2,0),"learn more") -> learn more | J17: These are additional names the product may be known as; These are simply names loaded without marking as primary. | K17: Batchloader / CorpBase Client | L17: Should not be marked "primary"; | S17: Chemical name synonyms | T17: Melting point | U17: Refractive index | W17: 3 | X17: FLUKA | Y17: F | Z17: Fluka | AA17: Not available in BatchLoader | BH17: Citations Form
D18: HOW do I use the job aid? | E18: STEP 1: Filter by 'data_definition_product_group' to identify top level product categorization | L18: should be unique from product's primary name | S18: Colour Index Number | T18: Molecular weight (daltons) | U18: Vapor Pressure | W18: 4 | X18: RIEDEL | Y18: R | Z18: Riedel-de-Haen | AA18: Not available in BatchLoader | BH18: Package Literals Template
E19: STEP 2: Filter by 'data_definition_product_type' to identify next level of product categorization | S19: Density | T19: Molecular weight | W19: 5 | X19: SUPELCO | Y19: U | Z19: Supelco | AB19: U2 | AC19: U2 | AD19: SU
E20: STEP 3: View required attributes (Attribute web_label) and priority assignment | G20: Properties | H20: Attributes | I20: =HYPERLINK(VLOOKUP(H20,'Learn More & Support'!$B:$D,2,0),"learn more") -> learn more | J20: Fixed Text Picklist | K20: Data Definition Job Aid in Confluence | L20: Reference data definition job aid for required fields | W20: 6 | X20: DIAG | Y20: D | Z20: Sigma | AA20: Not available in BatchLoader
E21: Priorities: | S21: PIM label data preview: | W21: 16 | X21: GENOSYS | Y21: G | Z21: Sigma | AA21: Not available in BatchLoader
E22: P1 = Required | G22: Trademarks | H22: Trademarks | I22: =HYPERLINK(VLOOKUP(H22,'Learn More & Support'!$B:$D,2,0),"learn more") -> learn more | J22: If applicable; Check Trademark table to verify if a trademark exists or to add new trademarks | K22: Batchloader / CorpBase Client (or Ticket) | L22: Value must exist in Trademark table | W22: 17 | X22: MM | Y22: M | Z22: Millipore | AB22: M5 | AC22: M5 | AD22: MI
E23: P2 = Critical | L23: If value exists: Batchloader / CorpBase Client | W23: 18 | X23: IVD | Y23: I | Z23: Sigma | AA23: Not available in BatchLoader
E24: P3 = Preferred | L24: If new value must be created: Enter a ticket. | W24: 19 | X24: TRINITY | Y24: Y | Z24: Sigma | AA24: Not available in BatchLoader
E25: STEP 4: Enter the provided product data into Batchloader/CorpBase PIM during NPI using the instructions provided | L25: Typical cycle time for adding/updating trademark table is ~4 weeks; | W25: 40 | X25: CERILLIAN | Y25: C | Z25: Cerilliant | AB25: C2 | AC25: C2 | AD25: CE
L26: don't just enter trademark symbols ® or ™
D27: UPDATE TO THE DATA DEF JOB AID / PDP CHECKLIST
D28: The data def job aid and PDP Checklists have now been combined into one file (this file). | G28: Aliases | H28: UNSPSC Code | I28: =HYPERLINK(VLOOKUP(H28,'Learn More & Support'!$B:$D,2,0),"learn more") -> learn more | J28: United Nations Standard Products and Services Code (UNSPSC); | K28: Batchloader / CorpBase Client | L28: CorpBase batchloader "Aliases" tab, drop down type: UNSPSC code
D29: Future updates to the the Data Definition job aid tab will automatically update the attributes/properties dynamic table on the PDP Checklist | L29: can be on substance level or product level
D30: This will ensure all PMs are using up to date product data recommendations during NPI and data def review
D31: Please be sure to always use the latest version of this file | G31: Imagery | H31: Product image | I31: =HYPERLINK(VLOOKUP(H31,'Learn More & Support'!$B:$D,2,0),"learn more") -> learn more | J31: CorpBase Graphics Object Load Template; 400 DPI or above | K31: CorpBase Graphics Request
H32: Image caption | I32: =HYPERLINK(VLOOKUP(H32,'Learn More & Support'!$B:$D,2,0),"learn more") -> learn more | J32: Load in same CorpBase Graphics Object Load Template file, using PM provided filenames and caption text | K32: CorpBase Graphics Request
H33: Chemical structure | I33: =HYPERLINK(VLOOKUP(H33,'Learn More & Support'!$B:$D,2,0),"learn more") -> learn more | J33: If applicable. Provide structure (ChemDraw) to structures@merckgroup.com | K33: structures@merckgroup.com | N33: Method 3: CorpBase | O33: enter the product number and brand you want to use on the names tab and hit validate.
N34: batchloader | O34: In this case, if anything comes back green, then that product number/brand already exists.
G35: Packaging | H35: Pack size (displayed in P&A) | I35: =HYPERLINK(VLOOKUP(H35,'Learn More & Support'!$B:$D,2,0),"learn more") -> learn more | J35: use Package Literals Template | K35: CorpBase Help Desk Request | L35: Ticket has to be submitted after Products are marked Ready in CorpBase. | N35: (Validation) | O35: Green=bad, product no/brand combination not in corpbase/RED=good
O36: (Also beware the red though if it says user doesn't have permissions to update product)
G37: Descriptions | H37: Enter the following prioritized description types at a minimum; additional descriptions can be entered | O37: So use the filter in the validation field - any blanks
H38: General Description | I38: =HYPERLINK(VLOOKUP(G37,'Learn More & Support'!$B:$D,2,0),"learn more") -> learn more | J38: Description type = General Description Long | K38: Batchloader / CorpBase Client | O38: or "user does not have permissions to edit product" those are ones that already exist)
H39: Application | J39: Description type = Application Long | K39: Batchloader / CorpBase Client
H40: Features & Benefits | J40: Description type = Features & Benefits Long | K40: Batchloader / CorpBase Client
G42: Documentation | H42: Product documents | I42: =HYPERLINK(VLOOKUP(H42,'Learn More & Support'!$B:$D,2,0),"learn more") -> learn more | J42: Contact business-specific lead for product documents | K42: Follow business specific process
G44: Peer Reviewed Papers | H44: Citations | I44: =HYPERLINK(VLOOKUP(H44,'Learn More & Support'!$B:$D,2,0),"learn more") -> learn more | J44: use Citations Form to enter PMIDs | K44: CorpBase Help Desk Request | L44: JIRA ticket submitted through CB Help Desk
G46: Related Products | H46: Related products | I46: =HYPERLINK(VLOOKUP(H46,'Learn More & Support'!$B:$D,2,0),"learn more") -> learn more | J46: Related to or Related from products can be added using the CorpBase batchloader or CorpBase Client | K46: Batchloader / CorpBase Client | L46: Other products must be created in CB
G48: Digital Optimization | H48: Keywords | I48: =HYPERLINK(VLOOKUP(H48,'Learn More & Support'!$B:$D,2,0),"learn more") -> learn more | J48: Added as names, name type = keyword | K48: Batchloader / CorpBase Client
H49: Meta title | I49: =HYPERLINK(VLOOKUP(H49,'Learn More & Support'!$B:$D,2,0),"learn more") -> learn more | J49: Added as names, name type = web meta title | K49: Batchloader / CorpBase Client
H50: Meta description | I50: =HYPERLINK(VLOOKUP(H50,'Learn More & Support'!$B:$D,2,0),"learn more") -> learn more | J50: Added as attribute = web meta description | K50: Batchloader / CorpBase Client
H51: Product Category page | I51: =HYPERLINK(VLOOKUP(H51,'Learn More & Support'!$B:$D,2,0),"learn more") -> learn more | J51: Provide product number + CorpBase brand + category page title | K51: CorpBase Help Desk Request | L51: Category Page must exist
H52: Call to Action | I52: =HYPERLINK(VLOOKUP(H52,'Learn More & Support'!$B:$D,2,0),"learn more") -> learn more | J52: See instructions and restrictions on selection | K52: Email Request (See instructions on EVA)
H53: Legacy Legal Entity | I53: =HYPERLINK(VLOOKUP(H53,'Learn More & Support'!$B:$D,2,0),"learn more") -> learn more | J53: Default "Merck/Sigma-Aldrich" to enable Product on ALL sites. Confirm with Product Data if a different option is selected. | K53: Merck/Sigma-Aldrich

Sheet Data Definition Job Aid
A1: STEP 1: filter by Column A and B; STEP 2: Reference Column E for required dataData Definition Alignment Date: 10-4-2024
A2: data_definition_product_group | B2: data_definition_product_type | C2: Attribute_web_label | D2: Priority | E2: Priority_new | F2: CB_batchloader_-_which_tab | G2: Please_use_drop_downs_and_select | H2: Notes | I2: Example_Product_Number | J2: Example_Data | K2: Facet_YN | L2: Facet_Label | M2: facet_requirements | N2: facet_string
A3: acids and bases | C3: CAS_NO | D3: Basic Data | E3: Priority 1 | F3: CAS | G3: Select TYPE, enter the CAS NUMBER, select PUBLISHING FLAG | H3: must be on the substance level | I3: 1.0183 | J3: 64-19-7 | K3: N
A4: acids and bases | C4: NAME_ENGLISH_1 | D4: Basic Data | E4: Priority 1 | F4: Names | G4: Choose NAME TYPE; PRM EN; ROOT NAME EN | H4: enter other keywords, names…etc. on this tab | I4: 1.00686 | J4: Sulfanilic acid | K4: N
A5: acids and bases | C5: NAME_SUFFIX_ENGLISH_1 | D5: Basic Data | E5: Priority 1 | F5: ProductAttributes | G5: Select product attributes using NAME SUFFIX SEQUENCE (1,2,3,4…etc) | I5: 1.00686 | J5: GR for analysis ACS,Reag. Ph Eur | K5: N
A6: acids and bases | C6: UNSPSC_CODE | D6: Basic Data | E6: Priority 1 | F6: Aliases | G6: drop down type: UNSPSC code | H6: can be on substance level or product level | I6: 1.00686 | J6: 12352106 | K6: N
A7: acids and bases | C7: concentration | D7: Facet driving attribute | E7: Priority 1 | F7: ProductAttributes | G7: ATTRIBUTE TYPE: Concentration | I7: 1.00713 | J7: 95-98% | K7: N
A8: acids and bases | C8: form | D8: Facet driving attribute | E8: Priority 1 | F8: ProductAttributes | G8: ATTRIBUTE TYPE: Physical Form | I8: 1.00682 | J8: solid | K8: Y | L8: Physical Form | M8: ?
A9: acids and bases | C9: grade | D9: Facet driving attribute | E9: Priority 1 | F9: ProductAttributes | G9: ATTRIBUTE TYPE: Special Grade and web special grade | H9: web special grade is facetable; but web special grade does not show on the PDP; special grade is the opposite | I9: 1.00686 | J9: ACS reagent | K9: Y | L9: Grade | M9: web special grade
A10: acids and bases | C10: assay | D10: High priority attribute | E10: Priority 2 | F10: ProductAttributes | G10: ATTRIBUTE TYPE: Assay | I10: 1.00686 | J10: ≥99.0-102.0% (acidimetric) | K10: Y | L10: Purity | M10: ?
A11: acids and bases | C11: InChI | D11: High priority attribute | E11: Priority 2 | F11: Aliases | G11: drop down type: InChl | H11: must be on the substance level | I11: 1.00686 | J11: 1S/C6H7NO3S/c7-5-1-3-6(4-2-5)11(8,9)10/h1-4H,7H2,(H,8,9,10) | K11: N
A12: acids and bases | C12: InChI key | D12: High priority attribute | E12: Priority 2 | F12: Aliases | G12: drop down type: InChl key | H12: must be on the substance level | I12: 1.00686 | J12: HVBSAKJJOYLTQU-UHFFFAOYSA-N | K12: N
A13: acids and bases | C13: pH | D13: High priority attribute | E13: Priority 2 | F13: ProductAttributes | G13: ATTRIBUTE TYPE: pH value | I13: 1.00686 | J13: 2.5 (20 °C, 10 g/L in H2O) | K13: Y | L13: pH | M13: ?
A14: acids and bases | C14: SMILES string | D14: High priority attribute | E14: Priority 2 | F14: Aliases | G14: drop down type: SMILES | H14: must be on the substance level; 30 characters or less; if more than 30 characters, raise a JIRA for CorpBase Helpdesk | I14: 1.00682 | J14: OC(=O)CCC(O)=O | K14: N
A15: acids and bases | C15: solubility | D15: High priority attribute | E15: Priority 2 | F15: ProductAttributes | G15: ATTRIBUTE TYPE: Solubility | I15: 1.00686 | J15: water: 10 g/L at 20 °C | K15: N
A16: acids and bases | C16: storage temp. | D16: High priority attribute | E16: Priority 2 | F16: ProductAttributes | G16: ATTRIBUTE TYPE: Storage Temp | I16: 1.00686 | J16: 15-25°C | K16: N
A17: acids and bases | C17: agency | D17: Low priority attribute | E17: Priority 3 | F17: ProductAttributes | G17: ATTRIBUTE TYPE: Agency/Method | H17: create separate lines for different values | I17: 1.00686 | J17: reag. Ph. Eur. | K17: Y | L17: Agency | N17: agency element
A18: acids and bases | C18: anion traces | D18: Low priority attribute | E18: Priority 3 | F18: ProductAttributes | G18: ATTRIBUTE TYPE: Anion Traces | I18: 1.00686 | J18: chloride (Cl-): ≤0.002%; nitrite (NO2-): ≤0.5 ppm; sulfate (SO42-): ≤0.01% | K18: N
A19: acids and bases | C19: bp | D19: Low priority attribute | E19: Priority 3 | F19: ProductAttributes | G19: ATTRIBUTE TYPE: Boiling Point | I19: 1.00682 | J19: 235 °C (lit.); 235 °C/1013 hPa | K19: Y | L19: boiling point | M19: ?
A20: acids and bases | C20: cation traces | D20: Low priority attribute | E20: Priority 3 | F20: ProductAttributes | G20: ATTRIBUTE TYPE: Cation Traces | I20: 1.00686 | J20: heavy metals (as Pb): ≤0.001% | K20: N
A21: acids and bases | C21: density | D21: Low priority attribute | E21: Priority 3 | F21: ProductAttributes | G21: ATTRIBUTE TYPE: Density | I21: 1.00686 | J21: 620 kg/m3 | K21: N
A22: acids and bases | C22: impurities | D22: Low priority attribute | E22: Priority 3 | F22: ProductAttributes | G22: ATTRIBUTE TYPE: Impurities | I22: 1.00452 | J22: ≤0.005 ppm Hg (Mercury) | K22: N
A23: acids and bases | C23: mp | D23: Low priority attribute | E23: Priority 3 | F23: ProductAttributes | G23: ATTRIBUTE TYPE: Melting Point | I23: 1.00686 | J23: 288 °C (decomposes) | K23: Y | L23: mp | M23: ?
A24: acids and bases | C24: refractive index | D24: Low priority attribute | E24: Priority 3 | F24: ProductAttributes | G24: ATTRIBUTE TYPE: Refractive Index | I24: 1.0183 | J24: n20/D 1.371 (lit.) | K24: N
A25: acids and bases | C25: vapor density | D25: Low priority attribute | E25: Priority 3 | F25: ProductAttributes | G25: ATTRIBUTE TYPE: Vapor density vs air | I25: 1.00714 | J25: <0.3 (25 °C, vs air) | K25: N
A26: acids and bases | C26: vapor pressure | D26: Low priority attribute | E26: Priority 3 | F26: ProductAttributes | G26: ATTRIBUTE TYPE: Vapor pressure | I26: 1.00452 | J26: 9.4 hPa ( 20 °C) | K26: N
A27: adapters | B27: pressure fittings | C27: NAME_ENGLISH_1 | D27: Basic Data | E27: Priority 1 | F27: Names | G27: Choose NAME TYPE; PRM EN; ROOT NAME EN | H27: enter other keywords, names…etc. on this tab | I27: PYR0CNT01 | J27: Pyrogard® D Point-of-Use Connector | K27: N
A28: adapters | B28: pressure fittings | C28: NAME_SUFFIX_ENGLISH_1 | D28: Basic Data | E28: Priority 1 | F28: ProductAttributes | G28: Select product attributes using NAME SUFFIX SEQUENCE (1,2,3,4…etc) | I28: PYR0CNT01 | J28: For use with Pyrogard® D ultrafiltration cartridge | K28: N
A29: adapters | B29: pressure fittings | C29: UNSPSC_CODE | D29: Basic Data | E29: Priority 1 | F29: Aliases | G29: drop down type: UNSPSC code | H29: can be on substance level or product level | I29: PYR0CNT01 | J29: 41104214 | K29: N
A30: adapters | B30: pressure fittings | C30: compatibility | D30: Facet driving attribute | E30: Priority 1 | F30: ProductAttributes | G30: ATTRIBUTE TYPE: ZM_COMPAT | H30: create separate lines for different values -- facet must use 1 or both of supplier and product line | I30: PYR0CNT01 | J30: for use with Milli-Q® Academic | K30: Y | L30: compatibility | M30: res=for use with, product line or manufacturer not empty | N30: Manufact Product line used with
A31: adapters | B31: pressure fittings | C31: fitting | D31: High priority attribute | E31: Priority 2 | F31: ProductAttributes | G31: ATTRIBUTE TYPE: fittings threads | I31: PYR0CNT01 | J31: 1/4 in. inlet connection; 1/4 in. outlet connection | K31: M | M31: part=thread | N31: fitsSize
A32: adapters | B32: pressure fittings | C32: packaging | D32: Low priority attribute | E32: Priority 3 | F32: ProductAttributes | G32: ATTRIBUTE TYPE: Packaging quantity | H32: facet only on pack_id (was NEVER used on the red site - utility is dubious) | I32: PYR0CNT01 | J32: pkg of 1 unit | K32: Y | L32: packaging | M32: pack_id | N32: pack_id
A33: adapters | B33: pressure fittings | C33: pore size | D33: Low priority attribute | E33: Priority 3 | F33: ProductAttributes | G33: ATTRIBUTE TYPE: Pore size | I33: PYR0CNT01 | J33: 0.45 μm pore size (CRW5 type) | K33: Y | L33: Pore size | M33: uom in um, or A, or kDa
A34: adapters | B34: pressure fittings | C34: shipped in | D34: Low priority attribute | E34: Priority 3 | F34: ProductAttributes | G34: ATTRIBUTE TYPE: Ice Shipping | I34: PYR0CNT01 | J34: dry ice, wet ice, ambient | K34: N
A35: adapters | C35: NAME_ENGLISH_1 | D35: Basic Data | E35: Priority 1 | F35: Names | G35: Choose NAME TYPE; PRM EN; ROOT NAME EN | H35: enter other keywords, names…etc. on this tab | I35: Z252301 | J35: Aldrich® anticlimb splash-guard adapter with fritted disc | K35: N
A36: adapters | C36: NAME_SUFFIX_ENGLISH_1 | D36: Basic Data | E36: Priority 1 | F36: ProductAttributes | G36: Select product attributes using NAME SUFFIX SEQUENCE (1,2,3,4…etc) | I36: Z252301 | J36: female Joint: ST/NS 24/40, male Joint: ST/NS 24/40, capacity 500 mL | K36: N
A37: adapters | C37: UNSPSC_CODE | D37: Basic Data | E37: Priority 1 | F37: Aliases | G37: drop down type: UNSPSC code | H37: can be on substance level or product level | I37: Z252301 | J37: 41121815 | K37: N
A38: adapters | C38: feature | D38: Facet driving attribute | E38: Priority 1 | F38: ProductAttributes | G38: ATTRIBUTE TYPE: Feature | H38: use the drop down to select a "Name" (for tubing i.d./for tubing o.d.) | I38: GE18114710 | J38: Wetted Material: Polyetheretherketone (PEEK); Connections: Fingertight 1/16"; ÄKTA® Systems | K38: N
A39: adapters | C39: fitting | D39: Facet driving attribute | E39: Priority 1 | F39: ProductAttributes | G39: ATTRIBUTE TYPE: fittings threads | I39: XX42T19H6 | J39: 1/4 in. hose barb; 3/4 in. sanitary clamp | K39: M | M39: part=thread | N39: fitsSize
A40: adapters | C40: joint | D40: Facet driving attribute | E40: Priority 1 | F40: ProductAttributes | G40: ATTRIBUTE TYPE: Standard Joint, choose part
A41: adapters | C41: material | D41: Facet driving attribute | E41: Priority 1 | F41: ProductAttributes | G41: ATTRIBUTE TYPE: Material | H41: use the drop down to select a "Part" | I41: GE18114710 | J41: PEEK | K41: Y
A42: adapters | C42: capacity | D42: High priority attribute | E42: Priority 2 | F42: ProductAttributes | G42: ATTRIBUTE TYPE: composite dimension | H42: use the drop down in "part" and select the part; "Type1" and select "capacity" | I42: SYNA274100 | J42: 100 mL | K42: Y | L42: Capacity(uom) | M42: uom in L or mL
A43: adapters | C43: manufacturer/tradename | D43: High priority attribute | E43: Priority 2 | F43: ProductAttributes | G43: ATTRIBUTE TYPE: Manufacturer designation | H43: facets supplier co only (currently - Product line the attribute also facetable but not the PL element in Manuf des. Yet) | I43: SYNA711420 | J43: Synthware A711420 | K43: Y | L43: Manufacturer | M43: supplier co | N43: supplier co
A44: adapters | C44: O.D. | D44: High priority attribute | E44: Priority 2 | F44: ProductAttributes | G44: ATTRIBUTE TYPE: Composite dimension | H44: use the drop down in "Type1" and select "O.D." | I44: GE18114710 | J44: (1/16 in.) | K44: Y | L44: O.D.(in)/O.D.(mm) | M44: type=OD and uom in mm or in.
A45: adapters | C45: packaging | D45: High priority attribute | E45: Priority 2 | F45: ProductAttributes | G45: ATTRIBUTE TYPE: Packaging quantity | H45: facet only on pack_id (was NEVER used on the red site - utility is dubious) | I45: SYNA711420 | J45: pkg of 1 ea | K45: Y | L45: packaging | M45: pack_id | N45: pack_id
A46: adsorbents | B46: carbon | C46: NAME_ENGLISH_1 | D46: Basic Data | E46: Priority 1 | F46: Names | G46: Choose NAME TYPE; PRM EN; ROOT NAME EN | H46: enter other keywords, names…etc. on this tab | I46: 31616 | J46: Activated charcoa | K46: N
A47: adsorbents | B47: carbon | C47: NAME_SUFFIX_ENGLISH_1 | D47: Basic Data | E47: Priority 1 | F47: ProductAttributes | G47: Select product attributes using NAME SUFFIX SEQUENCE (1,2,3,4…etc) | I47: 31616 | J47: puriss. p.a., powder | K47: N
A48: adsorbents | B48: carbon | C48: UNSPSC_CODE | D48: Basic Data | E48: Priority 1 | F48: Aliases | G48: drop down type: UNSPSC code | H48: can be on substance level or product level | I48: 31616 | J48: 23201100 | K48: N
A49: adsorbents | B49: carbon | C49: form | D49: Facet driving attribute | E49: Priority 1 | F49: ProductAttributes | G49: ATTRIBUTE TYPE: Physical Form | K49: Y | L49: Physical Form
A50: adsorbents | B50: carbon | C50: matrix | D50: Facet driving attribute | E50: Priority 1 | F50: ProductAttributes | G50: ATTRIBUTE TYPE: Matrix | I50: 31616 | J50: Carbon | K50: N
A51: adsorbents | B51: carbon | C51: matrix active group | D51: Facet driving attribute | E51: Priority 1 | F51: ProductAttributes | G51: ATTRIBUTE TYPE: Matrix active group | I51: 31616 | J51: Carbon | K51: N
A52: adsorbents | B52: carbon | C52: separation technique | D52: Facet driving attribute | E52: Priority 1 | F52: ProductAttributes | G52: ATTRIBUTE TYPE: Chromatography Mode | H52: use the drop down in "MODE" | I52: 31616 | J52: reversed phase | K52: Y | L52: separation technique
A53: adsorbents | B53: carbon | C53: technique(s) | D53: Facet driving attribute | E53: Priority 1 | F53: ProductAttributes | G53: ATTRIBUTE TYPE: Titertest | H53: use the drop down in "METHOD" | K53: Y | L53: Technique | M53: method | N53: method
A54: adsorbents | B54: carbon | C54: density | D54: High priority attribute | E54: Priority 2 | F54: ProductAttributes | G54: ATTRIBUTE TYPE: Density | K54: N
A55: adsorbents | B55: carbon | C55: packaging | D55: High priority attribute | E55: Priority 2 | F55: ProductAttributes | G55: ATTRIBUTE TYPE: Packaging quantity | H55: facet only on pack_id (was NEVER used on the red site - utility is dubious) | K55: Y | L55: packaging | M55: pack_id | N55: pack_id
A56: adsorbents | B56: carbon | C56: particle size | D56: High priority attribute | E56: Priority 2 | F56: ProductAttributes | G56: ATTRIBUTE TYPE: Particle Dimension | H56: use the drop down in "Type" and select "particle size" | K56: Y | L56: Particle size(um) | M56: type=particle size and uom in um
A57: adsorbents | B57: carbon | C57: pore size | D57: High priority attribute | E57: Priority 2 | F57: ProductAttributes | G57: ATTRIBUTE TYPE: Pore size | K57: Y | L57: Pore size | M57: uom in um, or A, or kDa
A58: adsorbents | B58: carbon | C58: surface area | D58: High priority attribute | E58: Priority 2 | F58: ProductAttributes | G58: ATTRIBUTE TYPE: Surface dimension | H58: use the drop down in "TYPE" and select "surface area" | K58: N
A59: adsorbents | B59: tlc | C59: NAME_ENGLISH_1 | D59: Basic Data | E59: Priority 1 | F59: Names | G59: Choose NAME TYPE; PRM EN; ROOT NAME EN | H59: enter other keywords, names…etc. on this tab | K59: N
A60: adsorbents | B60: tlc | C60: NAME_SUFFIX_ENGLISH_1 | D60: Basic Data | E60: Priority 1 | F60: ProductAttributes | G60: Select product attributes using NAME SUFFIX SEQUENCE (1,2,3,4…etc) | K60: N
A61: adsorbents | B61: tlc | C61: UNSPSC_CODE | D61: Basic Data | E61: Priority 1 | F61: Aliases | G61: drop down type: UNSPSC code | H61: can be on substance level or product level | K61: N
A62: adsorbents | B62: tlc | C62: material | D62: Facet driving attribute | E62: Priority 1 | F62: ProductAttributes | G62: ATTRIBUTE TYPE: Material | H62: use the drop down to select a "Part" | K62: Y
A63: adsorbents | B63: tlc | C63: technique(s) | D63: Facet driving attribute | E63: Priority 1 | F63: ProductAttributes | G63: ATTRIBUTE TYPE: Titertest | H63: use the drop down in "METHOD" | K63: Y | L63: Technique | M63: method | N63: method
A64: adsorbents | B64: tlc | C64: feature | D64: High priority attribute | E64: Priority 2 | F64: ProductAttributes | G64: ATTRIBUTE TYPE: Feature | H64: use the drop down to select a "Name" (binder/fluorescent indicator) | K64: Y | L64: Binder, Fluorescent
A65: adsorbents | B65: tlc | C65: pore size | D65: High priority attribute | E65: Priority 2 | F65: ProductAttributes | G65: ATTRIBUTE TYPE: Pore size | K65: Y | L65: Pore size | M65: uom in um, or A, or kDa
A66: adsorbents | C66: CAS_NO | D66: Basic Data | E66: Priority 1 | F66: CAS | G66: Select TYPE, enter the CAS NUMBER, select PUBLISHING FLAG | H66: must be on the substance level | I66: 30-0050 | J66: 14807-96-6 | K66: N
A67: adsorbents | C67: NAME_ENGLISH_1 | D67: Basic Data | E67: Priority 1 | F67: Names | G67: Choose NAME TYPE; PRM EN; ROOT NAME EN | H67: enter other keywords, names…etc. on this tab | I67: 1.07711 | J67: Sea sand | K67: N
A68: adsorbents | C68: NAME_SUFFIX_ENGLISH_1 | D68: Basic Data | E68: Priority 1 | F68: ProductAttributes | G68: Select product attributes using NAME SUFFIX SEQUENCE (1,2,3,4…etc) | I68: 1.07711 | J68: extra pure | K68: N
A69: adsorbents | C69: UNSPSC_CODE | D69: Basic Data | E69: Priority 1 | F69: Aliases | G69: drop down type: UNSPSC code | H69: can be on substance level or product level | I69: 1.07711 | J69: 11111701 | K69: N
A70: adsorbents | C70: diam. | D70: Facet driving attribute | E70: Priority 1 | F70: ProductAttributes | G70: ATTRIBUTE TYPE: Composite dimension | H70: use the drop down in "Type1" and select "diam." -- facet diam uom mm only | I70: 51127 | J70: ~4 mm | K70: Y | L70: Diameter(mm) | M70: type=diam. or D and uom in mm
A71: adsorbents | C71: form | D71: Facet driving attribute | E71: Priority 1 | F71: ProductAttributes | G71: ATTRIBUTE TYPE: Physical Form | I71: 1.07711 | J71: solid | K71: Y | L71: Physical Form
A72: adsorbents | C72: grade | D72: Facet driving attribute | E72: Priority 1 | F72: ProductAttributes | G72: ATTRIBUTE TYPE: Special Grade and web special grade | H72: web special grade is facetable; but web special grade does not show on the PDP; special grade is the opposite | I72: 31616 | J72: puriss. p.a. | K72: Y | L72: Special Grade
A73: adsorbents | C73: particle size | D73: Facet driving attribute | E73: Priority 1 | F73: ProductAttributes | G73: ATTRIBUTE TYPE: Particle Dimension | H73: use the drop down in "Type" and select "particle size" | I73: 49593 | J73: ≤45 μm | K73: Y | L73: Particle size(um) | M73: type=particle size and uom in um
A74: adsorbents | C74: pore size | D74: Facet driving attribute | E74: Priority 1 | F74: ProductAttributes | G74: ATTRIBUTE TYPE: Pore size | I74: 10184 | J74: ~0.04 cm3/g mesoporosity; ~0.35 cm3/g microporosity; ~4-11 pore diameter | K74: Y | L74: Pore size | M74: uom in um, or A, or kDa
A75: adsorbents | C75: SMILES string | D75: Facet driving attribute | E75: Priority 1 | F75: Aliases | G75: drop down type: SMILES | H75: must be on the substance level; 30 characters or less; if more than 30 characters, raise a JIRA for CorpBase Helpdesk | I75: 31616 | J75: [C] | K75: N
A76: adsorbents | C76: surface area | D76: Facet driving attribute | E76: Priority 1 | F76: ProductAttributes | G76: ATTRIBUTE TYPE: Surface dimension | H76: use the drop down in "TYPE" and select "surface area" | I76: 10184 | J76: ~975 m2/g | K76: N
A77: adsorbents | C77: assay | D77: High priority attribute | E77: Priority 2 | F77: ProductAttributes | G77: ATTRIBUTE TYPE: Assay | I77: 1.03874 | J77: 30 - 50% (Na2CO3, acidimetric) | K77: Y | L77: Purity
A78: adsorbents | C78: composition | D78: High priority attribute | E78: Priority 2 | F78: ProductAttributes | G78: ATTRIBUTE TYPE: Chemical Composition | I78: 49593 | J78: Al2O3, 0.9%; CaO, 3.7%; Na2O, 0.9% | K78: M | L78: composition
A79: adsorbents | C79: InChI | D79: High priority attribute | E79: Priority 2 | F79: Aliases | G79: drop down type: InChl | H79: must be on the substance level | I79: 1.07711 | J79: 1S/O2Si/c1-3-2 | K79: N
A80: adsorbents | C80: InChI key | D80: High priority attribute | E80: Priority 2 | F80: Aliases | G80: drop down type: InChl key | H80: must be on the substance level | I80: 1.07711 | J80: VYPSYNLAJGMNEJ-UHFFFAOYSA-N | K80: N
A81: adsorbents | C81: matrix | D81: High priority attribute | E81: Priority 2 | F81: ProductAttributes | G81: ATTRIBUTE TYPE: Matrix | I81: 31616 | J81: Carbon | K81: N
A82: adsorbents | C82: packaging | D82: High priority attribute | E82: Priority 2 | F82: ProductAttributes | G82: ATTRIBUTE TYPE: Packaging quantity | H82: facet only on pack_id (was NEVER used on the red site - utility is dubious) | I82: 10184 | J82: bottle of 10 g | K82: Y | L82: packaging | M82: pack_id | N82: pack_id
A83: adsorbents | C83: pH | D83: High priority attribute | E83: Priority 2 | F83: ProductAttributes | G83: ATTRIBUTE TYPE: pH value | I83: 1.07711 | J83: 5-8 (20 °C, 400 g/L in H2O, slurry) | K83: Y | L83: pH
A84: adsorbents | C84: autoignition temp. | D84: Low priority attribute | E84: Priority 3 | F84: ProductAttributes | G84: ATTRIBUTE TYPE: Autoignition temp | H84: must be on the substance level | I84: 31616 | J84: 842 °F | K84: N
A85: adsorbents | C85: availability | D85: Low priority attribute | E85: Priority 3 | F85: ProductAttributes | G85: ATTRIBUTE TYPE: Restriction | H85: use the drop down in "Availability restriction" and select a drop down in "RestrLoc" | I85: 30-0050 | J85: available only in Japan | K85: N
A86: adsorbents | C86: bp | D86: Low priority attribute | E86: Priority 3 | F86: ProductAttributes | G86: ATTRIBUTE TYPE: Boiling Point | I86: 1.07711 | J86: >2200 °C/1013 hPa | K86: Y | L86: boiling point
A87: adsorbents | C87: bulk density | D87: Low priority attribute | E87: Priority 3 | F87: ProductAttributes | G87: ATTRIBUTE TYPE: Bulk Density | I87: 1.07711 | J87: 1400 kg/m3 | K87: N
A88: adsorbents | C88: cation traces | D88: Low priority attribute | E88: Priority 3 | F88: ProductAttributes | G88: ATTRIBUTE TYPE: Cation Traces | I88: 31616 | J88: Cu: ≤25 mg/kg | K88: N
A89: adsorbents | C89: density | D89: Low priority attribute | E89: Priority 3 | F89: ProductAttributes | G89: ATTRIBUTE TYPE: Density | I89: 1.07711 | J89: 2.65 g/cm3 at 20 °C | K89: N
A90: adsorbents | C90: impurities | D90: Low priority attribute | E90: Priority 3 | F90: ProductAttributes | G90: ATTRIBUTE TYPE: Impurities | I90: 1.07711 | J90: ≤0.5% HCl solubles | K90: N
A91: adsorbents | C91: loss | D91: Low priority attribute | E91: Priority 3 | F91: ProductAttributes | G91: ATTRIBUTE TYPE: Loss | I91: 31616 | J91: ≤8% loss on drying, 120 °C | K91: N
A92: adsorbents | C92: manufacturer/tradename | D92: Low priority attribute | E92: Priority 3 | F92: ProductAttributes | G92: ATTRIBUTE TYPE: Manufacturer designation | H92: facets supplier co only (currently - Product line the attribute also facetable but not the PL element in Manuf des. Yet) | I92: 51127 | J92: Norit® RB4C | K92: Y | L92: Manufacturer | M92: supplier co | N92: supplier co
A93: adsorbents | C93: mp | D93: Low priority attribute | E93: Priority 3 | F93: ProductAttributes | G93: ATTRIBUTE TYPE: Melting Point | I93: 1.07711 | J93: 1713 °C | K93: Y | L93: mp
A94: adsorbents | C94: parameter | D94: Low priority attribute | E94: Priority 3 | F94: ProductAttributes | G94: ATTRIBUTE TYPE: Operating parameter | I94: 10184 | J94: 400 °C max. temp. | K94: N
A95: adsorbents | C95: technique(s) | D95: Low priority attribute | E95: Priority 3 | F95: ProductAttributes | G95: ATTRIBUTE TYPE: Titertest | H95: use the drop down in "METHOD" | I95: 31616 | J95: LPLC: suitable; tissue culture: suitable | K95: Y | L95: Technique | M95: method | N95: method
A96: adsorbents | C96: vapor pressure | D96: Low priority attribute | E96: Priority 3 | F96: ProductAttributes | G96: ATTRIBUTE TYPE: Vapor pressure | I96: 31616 | J96: <0.1 mmHg ( 20 °C) | K96: N
A97: air monitoring tubes and devices | C97: NAME_ENGLISH_1 | D97: Basic Data | E97: Priority 1 | F97: Names | G97: Choose NAME TYPE; PRM EN; ROOT NAME EN | H97: enter other keywords, names…etc. on this tab | I97: 20032 | J97: ORBO™ 506 Activated Silica Gel (45/60) 300/150 mg | K97: N
A98: air monitoring tubes and devices | C98: NAME_SUFFIX_ENGLISH_1 | D98: Basic Data | E98: Priority 1 | F98: ProductAttributes | G98: Select product attributes using NAME SUFFIX SEQUENCE (1,2,3,4…etc) | I98: 20032 | J98: W,W,W separators, O.D. × L 8 mm × 75 mm, pkg of 50 ea | K98: N
A99: air monitoring tubes and devices | C99: UNSPSC_CODE | D99: Basic Data | E99: Priority 1 | F99: Aliases | G99: drop down type: UNSPSC code | H99: can be on substance level or product level | K99: N
A100: air monitoring tubes and devices | C100: agency | D100: Facet driving attribute | E100: Priority 1 | F100: ProductAttributes | G100: ATTRIBUTE TYPE: Agency/Method | H100: create separate lines for different values | I100: 20032 | J100: NIOSH 2007 | K100: Y | L100: Agency
...

Sheet LOGIC
A1: Dynamic Cat1 | B1: Dynamic Cat2 | D1: UNIQUE GROUP | E1: UNIQUE TYPE | H1: PULLED FROM DD JOB AID --> | I1: data_definition_product_group | J1: data_definition_product_type | K1: Attribute_web_label | L1: Priority | M1: Priority_new | N1: CB_batchloader_-_which_tab | O1: Please_use_drop_downs_and_select | P1: Notes | Q1: Example_Product_Number | R1: Example_Data | S1: Facet_YN | T1: Facet_Label | U1: facet_requirements | V1: facet_string
A2: {=_xlfn.UNIQUE(_xlfn._xlws.FILTER(D2:D1000000,(D2:D1000000<>"(no product type)") * (D2:D1000000<>"")))} -> 1. Select Product Group | B2: {=IFERROR(_xlfn._xlws.FILTER(E2:E1000000,D2:D1000000='PDP Checklist'!$I$7),"Select Product Type")} -> various | D2: {=IF(_xlfn.UNIQUE(I2:J1000000)=0, "(no product type)", _xlfn.UNIQUE(I2:J1000000))} -> 1. Select Product Group | E2: 2. Select Product Type | H2: filtered "Basic Data" out unique (some dups in DD) | I2: 1. Select Product Group | J2: 2. Select Product Type
A3: acids and bases | D3: acids and bases | E3: (no product type) | G3: Combine Dynamic group and type columns --> | H3: {=INDEX(_xlfn.ANCHORARRAY(I3), 0, 1)&IF(INDEX(_xlfn.ANCHORARRAY(I3), 0, 2)=0,"(no product type)",INDEX(_xlfn.ANCHORARRAY(I3), 0, 2))} -> acids and bases(no product type) | I3: {=_xlfn.UNIQUE(_xlfn._xlws.FILTER('Data Definition Job Aid'!A3:N999552,('Data Definition Job Aid'!D3:D999552<>"Basic Data") * ('Data Definition Job Aid'!D3:D999552<>"")))} -> acids and bases | J3: 0 | K3: concentration | L3: Facet driving attribute | M3: Priority 1 | N3: ProductAttributes | O3: ATTRIBUTE TYPE: Concentration | P3: 0 | Q3: 1.00713 | R3: 95-98% | S3: N | T3: 0 | U3: 0 | V3: 0
A4: adapters | D4: adapters | E4: pressure fittings | H4: acids and bases(no product type) | I4: acids and bases | J4: 0 | K4: form | L4: Facet driving attribute | M4: Priority 1 | N4: ProductAttributes | O4: ATTRIBUTE TYPE: Physical Form | P4: 0 | Q4: 1.00682 | R4: solid | S4: Y | T4: Physical Form | U4: ? | V4: 0
A5: adsorbents | D5: adapters | E5: (no product type) | H5: acids and bases(no product type) | I5: acids and bases | J5: 0 | K5: grade | L5: Facet driving attribute | M5: Priority 1 | N5: ProductAttributes | O5: ATTRIBUTE TYPE: Special Grade and web special grade | P5: web special grade is facetable; but web special grade does not show on the PDP; special grade is the opposite | Q5: 1.00686 | R5: ACS reagent | S5: Y | T5: Grade | U5: web special grade | V5: 0
A6: air monitoring tubes and devices | D6: adsorbents | E6: carbon | H6: acids and bases(no product type) | I6: acids and bases | J6: 0 | K6: assay | L6: High priority attribute | M6: Priority 2 | N6: ProductAttributes | O6: ATTRIBUTE TYPE: Assay | P6: 0 | Q6: 1.00686 | R6: ≥99.0-102.0% (acidimetric) | S6: Y | T6: Purity | U6: ? | V6: 0
A7: amino acids | D7: adsorbents | E7: tlc | H7: acids and bases(no product type) | I7: acids and bases | J7: 0 | K7: InChI | L7: High priority attribute | M7: Priority 2 | N7: Aliases | O7: drop down type: InChl | P7: must be on the substance level | Q7: 1.00686 | R7: 1S/C6H7NO3S/c7-5-1-3-6(4-2-5)11(8,9)10/h1-4H,7H2,(H,8,9,10) | S7: N | T7: 0 | U7: 0 | V7: 0
A8: analytical vials | D8: adsorbents | E8: (no product type) | H8: acids and bases(no product type) | I8: acids and bases | J8: 0 | K8: InChI key | L8: High priority attribute | M8: Priority 2 | N8: Aliases | O8: drop down type: InChl key | P8: must be on the substance level | Q8: 1.00686 | R8: HVBSAKJJOYLTQU-UHFFFAOYSA-N | S8: N | T8: 0 | U8: 0 | V8: 0
A9: antibiotics | D9: air monitoring tubes and devices | E9: (no product type) | H9: acids and bases(no product type) | I9: acids and bases | J9: 0 | K9: pH | L9: High priority attribute | M9: Priority 2 | N9: ProductAttributes | O9: ATTRIBUTE TYPE: pH value | P9: 0 | Q9: 1.00686 | R9: 2.5 (20 °C, 10 g/L in H2O) | S9: Y | T9: pH | U9: ? | V9: 0
A10: antibodies | D10: amino acids | E10: (no product type) | H10: acids and bases(no product type) | I10: acids and bases | J10: 0 | K10: SMILES string | L10: High priority attribute | M10: Priority 2 | N10: Aliases | O10: drop down type: SMILES | P10: must be on the substance level; 30 characters or less; if more than 30 characters, raise a JIRA for CorpBase Helpdesk | Q10: 1.00682 | R10: OC(=O)CCC(O)=O | S10: N | T10: 0 | U10: 0 | V10: 0
A11: antibody antigens | D11: analytical vials | E11: (no product type) | H11: acids and bases(no product type) | I11: acids and bases | J11: 0 | K11: solubility | L11: High priority attribute | M11: Priority 2 | N11: ProductAttributes | O11: ATTRIBUTE TYPE: Solubility | P11: 0 | Q11: 1.00686 | R11: water: 10 g/L at 20 °C | S11: N | T11: 0 | U11: 0 | V11: 0
A12: bags | D12: antibiotics | E12: (no product type) | H12: acids and bases(no product type) | I12: acids and bases | J12: 0 | K12: storage temp. | L12: High priority attribute | M12: Priority 2 | N12: ProductAttributes | O12: ATTRIBUTE TYPE: Storage Temp | P12: 0 | Q12: 1.00686 | R12: 15-25°C | S12: N | T12: 0 | U12: 0 | V12: 0
A13: balances | D13: antibodies | E13: primary monoclonal | H13: acids and bases(no product type) | I13: acids and bases | J13: 0 | K13: agency | L13: Low priority attribute | M13: Priority 3 | N13: ProductAttributes | O13: ATTRIBUTE TYPE: Agency/Method | P13: create separate lines for different values | Q13: 1.00686 | R13: reag. Ph. Eur. | S13: Y | T13: Agency | U13: 0 | V13: agency element
A14: battery materials | D14: antibodies | E14: primary polyclonal | H14: acids and bases(no product type) | I14: acids and bases | J14: 0 | K14: anion traces | L14: Low priority attribute | M14: Priority 3 | N14: ProductAttributes | O14: ATTRIBUTE TYPE: Anion Traces | P14: 0 | Q14: 1.00686 | R14: chloride (Cl-): ≤0.002%; nitrite (NO2-): ≤0.5 ppm; sulfate (SO42-): ≤0.01% | S14: N | T14: 0 | U14: 0 | V14: 0
A15: beakers | D15: antibodies | E15: secondary | H15: acids and bases(no product type) | I15: acids and bases | J15: 0 | K15: bp | L15: Low priority attribute | M15: Priority 3 | N15: ProductAttributes | O15: ATTRIBUTE TYPE: Boiling Point | P15: 0 | Q15: 1.00682 | R15: 235 °C (lit.); 235 °C/1013 hPa | S15: Y | T15: boiling point | U15: ? | V15: 0
A16: bioinks | D16: antibodies | E16: various | H16: acids and bases(no product type) | I16: acids and bases | J16: 0 | K16: cation traces | L16: Low priority attribute | M16: Priority 3 | N16: ProductAttributes | O16: ATTRIBUTE TYPE: Cation Traces | P16: 0 | Q16: 1.00686 | R16: heavy metals (as Pb): ≤0.001% | S16: N | T16: 0 | U16: 0 | V16: 0
A17: boronic acids and mida boronates | D17: antibody antigens | E17: (no product type) | H17: acids and bases(no product type) | I17: acids and bases | J17: 0 | K17: density | L17: Low priority attribute | M17: Priority 3 | N17: ProductAttributes | O17: ATTRIBUTE TYPE: Density | P17: 0 | Q17: 1.00686 | R17: 620 kg/m3 | S17: N | T17: 0 | U17: 0 | V17: 0
A18: bottles | D18: bags | E18: assemblies | H18: acids and bases(no product type) | I18: acids and bases | J18: 0 | K18: impurities | L18: Low priority attribute | M18: Priority 3 | N18: ProductAttributes | O18: ATTRIBUTE TYPE: Impurities | P18: 0 | Q18: 1.00452 | R18: ≤0.005 ppm Hg (Mercury) | S18: N | T18: 0 | U18: 0 | V18: 0
A19: bsm | D19: bags | E19: sample | H19: acids and bases(no product type) | I19: acids and bases | J19: 0 | K19: mp | L19: Low priority attribute | M19: Priority 3 | N19: ProductAttributes | O19: ATTRIBUTE TYPE: Melting Point | P19: 0 | Q19: 1.00686 | R19: 288 °C (decomposes) | S19: Y | T19: mp | U19: ? | V19: 0
A20: buffers | D20: bags | E20: (no product type) | H20: acids and bases(no product type) | I20: acids and bases | J20: 0 | K20: refractive index | L20: Low priority attribute | M20: Priority 3 | N20: ProductAttributes | O20: ATTRIBUTE TYPE: Refractive Index | P20: 0 | Q20: 1.0183 | R20: n20/D 1.371 (lit.) | S20: N | T20: 0 | U20: 0 | V20: 0
A21: building blocks | D21: balances | E21: (no product type) | H21: acids and bases(no product type) | I21: acids and bases | J21: 0 | K21: vapor density | L21: Low priority attribute | M21: Priority 3 | N21: ProductAttributes | O21: ATTRIBUTE TYPE: Vapor density vs air | P21: 0 | Q21: 1.00714 | R21: <0.3 (25 °C, vs air) | S21: N | T21: 0 | U21: 0 | V21: 0
A22: burettes | D22: battery materials | E22: additive | H22: acids and bases(no product type) | I22: acids and bases | J22: 0 | K22: vapor pressure | L22: Low priority attribute | M22: Priority 3 | N22: ProductAttributes | O22: ATTRIBUTE TYPE: Vapor pressure | P22: 0 | Q22: 1.00452 | R22: 9.4 hPa ( 20 °C) | S22: N | T22: 0 | U22: 0 | V22: 0
A23: carbohydrates | D23: battery materials | E23: anode or cathode material | H23: adapterspressure fittings | I23: adapters | J23: pressure fittings | K23: compatibility | L23: Facet driving attribute | M23: Priority 1 | N23: ProductAttributes | O23: ATTRIBUTE TYPE: ZM_COMPAT | P23: create separate lines for different values -- facet must use 1 or both of supplier and product line | Q23: PYR0CNT01 | R23: for use with Milli-Q® Academic | S23: Y | T23: compatibility | U23: res=for use with, product line or manufacturer not empty | V23: Manufact Product line used with
A24: carts | D24: battery materials | E24: electrode | H24: adapterspressure fittings | I24: adapters | J24: pressure fittings | K24: fitting | L24: High priority attribute | M24: Priority 2 | N24: ProductAttributes | O24: ATTRIBUTE TYPE: fittings threads | P24: 0 | Q24: PYR0CNT01 | R24: 1/4 in. inlet connection; 1/4 in. outlet connection | S24: M | T24: 0 | U24: part=thread | V24: fitsSize
A25: catalysts and ligands | D25: battery materials | E25: electrolyte solid | H25: adapterspressure fittings | I25: adapters | J25: pressure fittings | K25: packaging | L25: Low priority attribute | M25: Priority 3 | N25: ProductAttributes | O25: ATTRIBUTE TYPE: Packaging quantity | P25: facet only on pack_id (was NEVER used on the red site - utility is dubious) | Q25: PYR0CNT01 | R25: pkg of 1 unit | S25: Y | T25: packaging | U25: pack_id | V25: pack_id
A26: cell lines | D26: battery materials | E26: electrolyte solution | H26: adapterspressure fittings | I26: adapters | J26: pressure fittings | K26: pore size | L26: Low priority attribute | M26: Priority 3 | N26: ProductAttributes | O26: ATTRIBUTE TYPE: Pore size | P26: 0 | Q26: PYR0CNT01 | R26: 0.45 μm pore size (CRW5 type) | S26: Y | T26: Pore size | U26: uom in um, or A, or kDa | V26: 0
A27: centrifuges | D27: battery materials | E27: solvent | H27: adapterspressure fittings | I27: adapters | J27: pressure fittings | K27: shipped in | L27: Low priority attribute | M27: Priority 3 | N27: ProductAttributes | O27: ATTRIBUTE TYPE: Ice Shipping | P27: 0 | Q27: PYR0CNT01 | R27: dry ice, wet ice, ambient | S27: N | T27: 0 | U27: 0 | V27: 0
A28: chelating and reducing agents | D28: beakers | E28: (no product type) | H28: adapters(no product type) | I28: adapters | J28: 0 | K28: feature | L28: Facet driving attribute | M28: Priority 1 | N28: ProductAttributes | O28: ATTRIBUTE TYPE: Feature | P28: use the drop down to select a "Name" (for tubing i.d./for tubing o.d.) | Q28: GE18114710 | R28: Wetted Material: Polyetheretherketone (PEEK); Connections: Fingertight 1/16"; ÄKTA® Systems | S28: N | T28: 0 | U28: 0 | V28: 0
A29: chromatography accessory | D29: bioinks | E29: (no product type) | H29: adapters(no product type) | I29: adapters | J29: 0 | K29: fitting | L29: Facet driving attribute | M29: Priority 1 | N29: ProductAttributes | O29: ATTRIBUTE TYPE: fittings threads | P29: 0 | Q29: XX42T19H6 | R29: 1/4 in. hose barb; 3/4 in. sanitary clamp | S29: M | T29: 0 | U29: part=thread | V29: fitsSize
A30: clamps | D30: boronic acids and mida boronates | E30: (no product type) | H30: adapters(no product type) | I30: adapters | J30: 0 | K30: joint | L30: Facet driving attribute | M30: Priority 1 | N30: ProductAttributes | O30: ATTRIBUTE TYPE: Standard Joint, choose part | P30: 0 | Q30: 0 | R30: 0 | S30: 0 | T30: 0 | U30: 0 | V30: 0
A31: closures | D31: bottles | E31: centrifuge | H31: adapters(no product type) | I31: adapters | J31: 0 | K31: material | L31: Facet driving attribute | M31: Priority 1 | N31: ProductAttributes | O31: ATTRIBUTE TYPE: Material | P31: use the drop down to select a "Part" | Q31: GE18114710 | R31: PEEK | S31: Y | T31: 0 | U31: 0 | V31: 0
A32: coating oligos | D32: bottles | E32: closed system and transfer | H32: adapters(no product type) | I32: adapters | J32: 0 | K32: capacity | L32: High priority attribute | M32: Priority 2 | N32: ProductAttributes | O32: ATTRIBUTE TYPE: composite dimension | P32: use the drop down in "part" and select the part; "Type1" and select "capacity" | Q32: SYNA274100 | R32: 100 mL | S32: Y | T32: Capacity(uom) | U32: uom in L or mL | V32: 0
A33: cofactors | D33: bottles | E33: dilution | H33: adapters(no product type) | I33: adapters | J33: 0 | K33: manufacturer/tradename | L33: High priority attribute | M33: Priority 2 | N33: ProductAttributes | O33: ATTRIBUTE TYPE: Manufacturer designation | P33: facets supplier co only (currently - Product line the attribute also facetable but not the PL element in Manuf des. Yet) | Q33: SYNA711420 | R33: Synthware A711420 | S33: Y | T33: Manufacturer | U33: supplier co | V33: supplier co
A34: combs | D34: bottles | E34: dropper | H34: adapters(no product type) | I34: adapters | J34: 0 | K34: O.D. | L34: High priority attribute | M34: Priority 2 | N34: ProductAttributes | O34: ATTRIBUTE TYPE: Composite dimension | P34: use the drop down in "Type1" and select "O.D." | Q34: GE18114710 | R34: (1/16 in.) | S34: Y | T34: O.D.(in)/O.D.(mm) | U34: type=OD and uom in mm or in. | V34: 0
A35: culture media | D35: bottles | E35: gas washing | H35: adapters(no product type) | I35: adapters | J35: 0 | K35: packaging | L35: High priority attribute | M35: Priority 2 | N35: ProductAttributes | O35: ATTRIBUTE TYPE: Packaging quantity | P35: facet only on pack_id (was NEVER used on the red site - utility is dubious) | Q35: SYNA711420 | R35: pkg of 1 ea | S35: Y | T35: packaging | U35: pack_id | V35: pack_id
A36: cylinder | D36: bottles | E36: general purpose and jars | H36: adsorbentscarbon | I36: adsorbents | J36: carbon | K36: form | L36: Facet driving attribute | M36: Priority 1 | N36: ProductAttributes | O36: ATTRIBUTE TYPE: Physical Form | P36: 0 | Q36: 0 | R36: 0 | S36: Y | T36: Physical Form | U36: 0 | V36: 0
A37: detergents | D37: bottles | E37: media and lab bottles | H37: adsorbentscarbon | I37: adsorbents | J37: carbon | K37: matrix | L37: Facet driving attribute | M37: Priority 1 | N37: ProductAttributes | O37: ATTRIBUTE TYPE: Matrix | P37: 0 | Q37: 31616 | R37: Carbon | S37: N | T37: 0 | U37: 0 | V37: 0
A38: dishes | D38: bottles | E38: pressure | H38: adsorbentscarbon | I38: adsorbents | J38: carbon | K38: matrix active group | L38: Facet driving attribute | M38: Priority 1 | N38: ProductAttributes | O38: ATTRIBUTE TYPE: Matrix active group | P38: 0 | Q38: 31616 | R38: Carbon | S38: N | T38: 0 | U38: 0 | V38: 0
A39: dispenser pumps | D39: bottles | E39: reagent | H39: adsorbentscarbon | I39: adsorbents | J39: carbon | K39: separation technique | L39: Facet driving attribute | M39: Priority 1 | N39: ProductAttributes | O39: ATTRIBUTE TYPE: Chromatography Mode | P39: use the drop down in "MODE" | Q39: 31616 | R39: reversed phase | S39: Y | T39: separation technique | U39: 0 | V39: 0
A40: documentation | D40: bottles | E40: roller | H40: adsorbentscarbon | I40: adsorbents | J40: carbon | K40: technique(s) | L40: Facet driving attribute | M40: Priority 1 | N40: ProductAttributes | O40: ATTRIBUTE TYPE: Titertest | P40: use the drop down in "METHOD" | Q40: 0 | R40: 0 | S40: Y | T40: Technique | U40: method | V40: method
A41: downstream | D41: bottles | E41: wash | H41: adsorbentscarbon | I41: adsorbents | J41: carbon | K41: density | L41: High priority attribute | M41: Priority 2 | N41: ProductAttributes | O41: ATTRIBUTE TYPE: Density | P41: 0 | Q41: 0 | R41: 0 | S41: N | T41: 0 | U41: 0 | V41: 0
A42: electron transfer salt | D42: bottles | E42: weighing and density | H42: adsorbentscarbon | I42: adsorbents | J42: carbon | K42: packaging | L42: High priority attribute | M42: Priority 2 | N42: ProductAttributes | O42: ATTRIBUTE TYPE: Packaging quantity | P42: facet only on pack_id (was NEVER used on the red site - utility is dubious) | Q42: 0 | R42: 0 | S42: Y | T42: packaging | U42: pack_id | V42: pack_id
A43: enzyme inhibitors | D43: bottles | E43: (no product type) | H43: adsorbentscarbon | I43: adsorbents | J43: carbon | K43: particle size | L43: High priority attribute | M43: Priority 2 | N43: ProductAttributes | O43: ATTRIBUTE TYPE: Particle Dimension | P43: use the drop down in "Type" and select "particle size" | Q43: 0 | R43: 0 | S43: Y | T43: Particle size(um) | U43: type=particle size and uom in um | V43: 0
A44: enzyme substrates | D44: bsm | E44: (no product type) | H44: adsorbentscarbon | I44: adsorbents | J44: carbon | K44: pore size | L44: High priority attribute | M44: Priority 2 | N44: ProductAttributes | O44: ATTRIBUTE TYPE: Pore size | P44: 0 | Q44: 0 | R44: 0 | S44: Y | T44: Pore size | U44: uom in um, or A, or kDa | V44: 0
A45: enzymes | D45: buffers | E45: (no product type) | H45: adsorbentscarbon | I45: adsorbents | J45: carbon | K45: surface area | L45: High priority attribute | M45: Priority 2 | N45: ProductAttributes | O45: ATTRIBUTE TYPE: Surface dimension | P45: use the drop down in "TYPE" and select "surface area" | Q45: 0 | R45: 0 | S45: N | T45: 0 | U45: 0 | V45: 0
A46: esirna | D46: building blocks | E46: aldrich cpr | H46: adsorbentstlc | I46: adsorbents | J46: tlc | K46: material | L46: Facet driving attribute | M46: Priority 1 | N46: ProductAttributes | O46: ATTRIBUTE TYPE: Material | P46: use the drop down to select a "Part" | Q46: 0 | R46: 0 | S46: Y | T46: 0 | U46: 0 | V46: 0
A47: films and foils | D47: building blocks | E47: electronic | H47: adsorbentstlc | I47: adsorbents | J47: tlc | K47: technique(s) | L47: Facet driving attribute | M47: Priority 1 | N47: ProductAttributes | O47: ATTRIBUTE TYPE: Titertest | P47: use the drop down in "METHOD" | Q47: 0 | R47: 0 | S47: Y | T47: Technique | U47: method | V47: method
A48: filter paper | D48: building blocks | E48: protein degradation | H48: adsorbentstlc | I48: adsorbents | J48: tlc | K48: feature | L48: High priority attribute | M48: Priority 2 | N48: ProductAttributes | O48: ATTRIBUTE TYPE: Feature | P48: use the drop down to select a "Name" (binder/fluorescent indicator) | Q48: 0 | R48: 0 | S48: Y | T48: Binder, Fluorescent | U48: 0 | V48: 0
A49: filters | D49: building blocks | E49: (no product type) | H49: adsorbentstlc | I49: adsorbents | J49: tlc | K49: pore size | L49: High priority attribute | M49: Priority 2 | N49: ProductAttributes | O49: ATTRIBUTE TYPE: Pore size | P49: 0 | Q49: 0 | R49: 0 | S49: Y | T49: Pore size | U49: uom in um, or A, or kDa | V49: 0
A50: flasks | D50: burettes | E50: (no product type) | H50: adsorbents(no product type) | I50: adsorbents | J50: 0 | K50: diam. | L50: Facet driving attribute | M50: Priority 1 | N50: ProductAttributes | O50: ATTRIBUTE TYPE: Composite dimension | P50: use the drop down in "Type1" and select "diam." -- facet diam uom mm only | Q50: 51127 | R50: ~4 mm | S50: Y | T50: Diameter(mm) | U50: type=diam. or D and uom in mm | V50: 0
A51: flavors and fragrances | D51: carbohydrates | E51: glycoconjugate probes | H51: adsorbents(no product type) | I51: adsorbents | J51: 0 | K51: form | L51: Facet driving attribute | M51: Priority 1 | N51: ProductAttributes | O51: ATTRIBUTE TYPE: Physical Form | P51: 0 | Q51: 1.07711 | R51: solid | S51: Y | T51: Physical Form | U51: 0 | V51: 0
A52: forceps | D52: carbohydrates | E52: (no product type) | H52: adsorbents(no product type) | I52: adsorbents | J52: 0 | K52: grade | L52: Facet driving attribute | M52: Priority 1 | N52: ProductAttributes | O52: ATTRIBUTE TYPE: Special Grade and web special grade | P52: web special grade is facetable; but web special grade does not show on the PDP; special grade is the opposite | Q52: 31616 | R52: puriss. p.a. | S52: Y | T52: Special Grade | U52: 0 | V52: 0
A53: freezers | D53: carts | E53: (no product type) | H53: adsorbents(no product type) | I53: adsorbents | J53: 0 | K53: particle size | L53: Facet driving attribute | M53: Priority 1 | N53: ProductAttributes | O53: ATTRIBUTE TYPE: Particle Dimension | P53: use the drop down in "Type" and select "particle size" | Q53: 49593 | R53: ≤45 μm | S53: Y | T53: Particle size(um) | U53: type=particle size and uom in um | V53: 0
A54: funnels | D54: catalysts and ligands | E54: buchwald catalyts | H54: adsorbents(no product type) | I54: adsorbents | J54: 0 | K54: pore size | L54: Facet driving attribute | M54: Priority 1 | N54: ProductAttributes | O54: ATTRIBUTE TYPE: Pore size | P54: 0 | Q54: 10184 | R54: ~0.04 cm3/g mesoporosity; ~0.35 cm3/g microporosity; ~4-11 pore diameter | S54: Y | T54: Pore size | U54: uom in um, or A, or kDa | V54: 0
A55: gc columns | D55: catalysts and ligands | E55: cartridge system | H55: adsorbents(no product type) | I55: adsorbents | J55: 0 | K55: SMILES string | L55: Facet driving attribute | M55: Priority 1 | N55: Aliases | O55: drop down type: SMILES | P55: must be on the substance level; 30 characters or less; if more than 30 characters, raise a JIRA for CorpBase Helpdesk | Q55: 31616 | R55: [C] | S55: N | T55: 0 | U55: 0 | V55: 0
A56: gel casters | D56: catalysts and ligands | E56: chembeads | H56: adsorbents(no product type) | I56: adsorbents | J56: 0 | K56: surface area | L56: Facet driving attribute | M56: Priority 1 | N56: ProductAttributes | O56: ATTRIBUTE TYPE: Surface dimension | P56: use the drop down in "TYPE" and select "surface area" | Q56: 10184 | R56: ~975 m2/g | S56: N | T56: 0 | U56: 0 | V56: 0
A57: gel precursors | D57: catalysts and ligands | E57: microspheres | H57: adsorbents(no product type) | I57: adsorbents | J57: 0 | K57: assay | L57: High priority attribute | M57: Priority 2 | N57: ProductAttributes | O57: ATTRIBUTE TYPE: Assay | P57: 0 | Q57: 1.03874 | R57: 30 - 50% (Na2CO3, acidimetric) | S57: Y | T57: Purity | U57: 0 | V57: 0
A58: gene editing tools rnai | D58: catalysts and ligands | E58: photocatalysts | H58: adsorbents(no product type) | I58: adsorbents | J58: 0 | K58: composition | L58: High priority attribute | M58: Priority 2 | N58: ProductAttributes | O58: ATTRIBUTE TYPE: Chemical Composition | P58: 0 | Q58: 49593 | R58: Al2O3, 0.9%; CaO, 3.7%; Na2O, 0.9% | S58: M | T58: composition | U58: 0 | V58: 0
A59: general reagents and consumables | D59: catalysts and ligands | E59: (no product type) | H59: adsorbents(no product type) | I59: adsorbents | J59: 0 | K59: InChI | L59: High priority attribute | M59: Priority 2 | N59: Aliases | O59: drop down type: InChl | P59: must be on the substance level | Q59: 1.07711 | R59: 1S/O2Si/c1-3-2 | S59: N | T59: 0 | U59: 0 | V59: 0
A60: gloves | D60: cell lines | E60: general collection | H60: adsorbents(no product type) | I60: adsorbents | J60: 0 | K60: InChI key | L60: High priority attribute | M60: Priority 2 | N60: Aliases | O60: drop down type: InChl key | P60: must be on the substance level | Q60: 1.07711 | R60: VYPSYNLAJGMNEJ-UHFFFAOYSA-N | S60: N | T60: 0 | U60: 0 | V60: 0
A61: graduated or measuring cylinder | D61: cell lines | E61: human leukocyte antigen collection | H61: adsorbents(no product type) | I61: adsorbents | J61: 0 | K61: matrix | L61: High priority attribute | M61: Priority 2 | N61: ProductAttributes | O61: ATTRIBUTE TYPE: Matrix | P61: 0 | Q61: 31616 | R61: Carbon | S61: N | T61: 0 | U61: 0 | V61: 0
A62: grinders and homogenizers | D62: cell lines | E62: human random control collection | H62: adsorbents(no product type) | I62: adsorbents | J62: 0 | K62: packaging | L62: High priority attribute | M62: Priority 2 | N62: ProductAttributes | O62: ATTRIBUTE TYPE: Packaging quantity | P62: facet only on pack_id (was NEVER used on the red site - utility is dubious) | Q62: 10184 | R62: bottle of 10 g | S62: Y | T62: packaging | U62: pack_id | V62: pack_id
A63: hand tools | D63: cell lines | E63: hybridoma collection | H63: adsorbents(no product type) | I63: adsorbents | J63: 0 | K63: pH | L63: High priority attribute | M63: Priority 2 | N63: ProductAttributes | O63: ATTRIBUTE TYPE: pH value | P63: 0 | Q63: 1.07711 | R63: 5-8 (20 °C, 400 g/L in H2O, slurry) | S63: Y | T63: pH | U63: 0 | V63: 0
A64: heaters | D64: cell lines | E64: immortalized cell lines | H64: adsorbents(no product type) | I64: adsorbents | J64: 0 | K64: autoignition temp. | L64: Low priority attribute | M64: Priority 3 | N64: ProductAttributes | O64: ATTRIBUTE TYPE: Autoignition temp | P64: must be on the substance level | Q64: 31616 | R64: 842 °F | S64: N | T64: 0 | U64: 0 | V64: 0
A65: holders | D65: cell lines | E65: ipsc dervied neural cells | H65: adsorbents(no product type) | I65: adsorbents | J65: 0 | K65: availability | L65: Low priority attribute | M65: Priority 3 | N65: ProductAttributes | O65: ATTRIBUTE TYPE: Restriction | P65: use the drop down in "Availability restriction" and select a drop down in "RestrLoc" | Q65: 30-0050 | R65: available only in Japan | S65: N | T65: 0 | U65: 0 | V65: 0
A66: hormones | D66: cell lines | E66: primary cell lines | H66: adsorbents(no product type) | I66: adsorbents | J66: 0 | K66: bp | L66: Low priority attribute | M66: Priority 3 | N66: ProductAttributes | O66: ATTRIBUTE TYPE: Boiling Point | P66: 0 | Q66: 1.07711 | R66: >2200 °C/1013 hPa | S66: Y | T66: boiling point | U66: 0 | V66: 0
A67: hplc columns | D67: cell lines | E67: stem cell lines | H67: adsorbents(no product type) | I67: adsorbents | J67: 0 | K67: bulk density | L67: Low priority attribute | M67: Priority 3 | N67: ProductAttributes | O67: ATTRIBUTE TYPE: Bulk Density | P67: 0 | Q67: 1.07711 | R67: 1400 kg/m3 | S67: N | T67: 0 | U67: 0 | V67: 0
A68: hplc guard columns | D68: centrifuges | E68: adapter | H68: adsorbents(no product type) | I68: adsorbents | J68: 0 | K68: cation traces | L68: Low priority attribute | M68: Priority 3 | N68: ProductAttributes | O68: ATTRIBUTE TYPE: Cation Traces | P68: 0 | Q68: 31616 | R68: Cu: ≤25 mg/kg | S68: N | T68: 0 | U68: 0 | V68: 0
A69: instruments | D69: centrifuges | E69: bucket | H69: adsorbents(no product type) | I69: adsorbents | J69: 0 | K69: density | L69: Low priority attribute | M69: Priority 3 | N69: ProductAttributes | O69: ATTRIBUTE TYPE: Density | P69: 0 | Q69: 1.07711 | R69: 2.65 g/cm3 at 20 °C | S69: N | T69: 0 | U69: 0 | V69: 0
A70: ion meters | D70: centrifuges | E70: lid | H70: adsorbents(no product type) | I70: adsorbents | J70: 0 | K70: impurities | L70: Low priority attribute | M70: Priority 3 | N70: ProductAttributes | O70: ATTRIBUTE TYPE: Impurities | P70: 0 | Q70: 1.07711 | R70: ≤0.5% HCl solubles | S70: N | T70: 0 | U70: 0 | V70: 0
A71: kits | D71: centrifuges | E71: micro or compact or standard or plate or strip | H71: adsorbents(no product type) | I71: adsorbents | J71: 0 | K71: loss | L71: Low priority attribute | M71: Priority 3 | N71: ProductAttributes | O71: ATTRIBUTE TYPE: Loss | P71: 0 | Q71: 31616 | R71: ≤8% loss on drying, 120 °C | S71: N | T71: 0 | U71: 0 | V71: 0
A72: labels | D72: centrifuges | E72: rotor | H72: adsorbents(no product type) | I72: adsorbents | J72: 0 | K72: manufacturer/tradename | L72: Low priority attribute | M72: Priority 3 | N72: ProductAttributes | O72: ATTRIBUTE TYPE: Manufacturer designation | P72: facets supplier co only (currently - Product line the attribute also facetable but not the PL element in Manuf des. Yet) | Q72: 51127 | R72: Norit® RB4C | S72: Y | T72: Manufacturer | U72: supplier co | V72: supplier co
A73: ladders and markers | D73: centrifuges | E73: (no product type) | H73: adsorbents(no product type) | I73: adsorbents | J73: 0 | K73: mp | L73: Low priority attribute | M73: Priority 3 | N73: ProductAttributes | O73: ATTRIBUTE TYPE: Melting Point | P73: 0 | Q73: 1.07711 | R73: 1713 °C | S73: Y | T73: mp | U73: 0 | V73: 0
A74: lipids | D74: chelating and reducing agents | E74: (no product type) | H74: adsorbents(no product type) | I74: adsorbents | J74: 0 | K74: parameter | L74: Low priority attribute | M74: Priority 3 | N74: ProductAttributes | O74: ATTRIBUTE TYPE: Operating parameter | P74: 0 | Q74: 10184 | R74: 400 °C max. temp. | S74: N | T74: 0 | U74: 0 | V74: 0
A75: liquid chromatography media | D75: chromatography accessory | E75: (no product type) | H75: adsorbents(no product type) | I75: adsorbents | J75: 0 | K75: technique(s) | L75: Low priority attribute | M75: Priority 3 | N75: ProductAttributes | O75: ATTRIBUTE TYPE: Titertest | P75: use the drop down in "METHOD" | Q75: 31616 | R75: LPLC: suitable; tissue culture: suitable | S75: Y | T75: Technique | U75: method | V75: method
A76: liquid visual tests | D76: clamps | E76: (no product type) | H76: adsorbents(no product type) | I76: adsorbents | J76: 0 | K76: vapor pressure | L76: Low priority attribute | M76: Priority 3 | N76: ProductAttributes | O76: ATTRIBUTE TYPE: Vapor pressure | P76: 0 | Q76: 31616 | R76: <0.1 mmHg ( 20 °C) | S76: N | T76: 0 | U76: 0 | V76: 0
A77: magnetic beads | D77: closures | E77: conical erlenmeyer or shaker or trypsinizing | H77: air monitoring tubes and devices(no product type) | I77: air monitoring tubes and devices | J77: 0 | K77: agency | L77: Facet driving attribute | M77: Priority 1 | N77: ProductAttributes | O77: ATTRIBUTE TYPE: Agency/Method | P77: create separate lines for different values | Q77: 20032 | R77: NIOSH 2007 | S77: Y | T77: Agency | U77: 0 | V77: 0
A78: magnetic stir bars | D78: closures | E78: nmr or cuvette cap | H78: air monitoring tubes and devices(no product type) | I78: air monitoring tubes and devices | J78: 0 | K78: composition | L78: Facet driving attribute | M78: Priority 1 | N78: ProductAttributes | O78: ATTRIBUTE TYPE: Chemical Composition | P78: 0 | Q78: 20032 | R78: Bed A, 300 mg; Bed B, 150 mg | S78: M | T78: composition | U78: 0 | V78: 0
A79: membranes | D79: closures | E79: open top | H79: air monitoring tubes and devices(no product type) | I79: air monitoring tubes and devices | J79: 0 | K79: material | L79: Facet driving attribute | M79: Priority 1 | N79: ProductAttributes | O79: ATTRIBUTE TYPE: Material | P79: use the drop down to select a "Part" | Q79: 20032 | R79: W,W,W separators; silica gel | S79: Y | T79: 0 | U79: 0 | V79: 0
A80: metabolite libraries | D80: closures | E80: perforated lid | H80: air monitoring tubes and devices(no product type) | I80: air monitoring tubes and devices | J80: 0 | K80: I.D. | L80: High priority attribute | M80: Priority 2 | N80: ProductAttributes | O80: ATTRIBUTE TYPE: Composite dimension | P80: use the drop down in "Type1" and select "I.D." | Q80: 29024-U | R80: 1/4 in. | S80: Y | T80: ID (mm) | U80: choose type=I.D, uom must be in mm | V80: value
A81: metals and alloys | D81: closures | E81: septa | H81: air monitoring tubes and devices(no product type) | I81: air monitoring tubes and devices | J81: 0 | K81: O.D. | L81: High priority attribute | M81: Priority 2 | N81: ProductAttributes | O81: ATTRIBUTE TYPE: Composite dimension | P81: use the drop down in "Type1" and select "O.D." | Q81: 20069 | R81: 37 mm | S81: Y | T81: O.D.(in)/O.D.(mm) | U81: type=OD and uom in mm or in. | V81: 0
A82: microscope slides and chambers | D82: closures | E82: solid cap or stopper | H82: air monitoring tubes and devices(no product type) | I82: air monitoring tubes and devices | J82: 0 | K82: technique(s) | L82: High priority attribute | M82: Priority 2 | N82: ProductAttributes | O82: ATTRIBUTE TYPE: Titertest | P82: use the drop down in "METHOD" | Q82: 0 | R82: 0 | S82: Y | T82: Technique | U82: method | V82: method
A83: mirna mimics | D83: closures | E83: transfer or reactor | H83: air monitoring tubes and devices(no product type) | I83: air monitoring tubes and devices | J83: 0 | K83: volume | L83: High priority attribute | M83: Priority 2 | N83: ProductAttributes | O83: ATTRIBUTE TYPE: Composite dimension | P83: use the drop down in "Type1" and select "volume" | Q83: 21014 | R83: 3 mL | S83: Y | T83: Volume (uom) | U83: type=Volume and uom in mL, L, or uL | V83: 0
A84: model sets | D84: closures | E84: valves | H84: air monitoring tubes and devices(no product type) | I84: air monitoring tubes and devices | J84: 0 | K84: W | L84: High priority attribute | M84: Priority 2 | N84: ProductAttributes | O84: ATTRIBUTE TYPE: Composite dimension | P84: use the drop down in "Type1" and select "W" | Q84: 0 | R84: 0 | S84: Y | T84: Width (uom) | U84: type=W and uom is in mm or in | V84: 0
A85: nanoparticles | D85: coating oligos | E85: (no product type) | H85: air monitoring tubes and devices(no product type) | I85: air monitoring tubes and devices | J85: 0 | K85: feature | L85: Low priority attribute | M85: Priority 3 | N85: ProductAttributes | O85: ATTRIBUTE TYPE: Feature | P85: use the drop down to select a "Name" (preconditioned/fritted/precleaned) | Q85: 29530-U | R85: preconditioned; fritted | S85: N | T85: 0 | U85: 0 | V85: 0
A86: natural products | D86: cofactors | E86: (no product type) | H86: amino acids(no product type) | I86: amino acids | J86: 0 | K86: form | L86: Facet driving attribute | M86: Priority 1 | N86: ProductAttributes | O86: ATTRIBUTE TYPE: Physical Form | P86: 0 | Q86: 561505 | R86: solid | S86: Y | T86: Physical Form | U86: 0 | V86: 0
A87: needles | D87: combs | E87: (no product type) | H87: amino acids(no product type) | I87: amino acids | J87: 0 | K87: grade | L87: Facet driving attribute | M87: Priority 1 | N87: ProductAttributes | O87: ATTRIBUTE TYPE: Special Grade and web special grade | P87: web special grade is facetable; but web special grade does not show on the PDP; special grade is the opposite | Q87: 12805 | R87: purum | S87: Y | T87: grade | U87: 0 | V87: 0
A88: nucleotides and derivatives | D88: culture media | E88: cell separation | H88: amino acids(no product type) | I88: amino acids | J88: 0 | K88: assay | L88: High priority attribute | M88: Priority 2 | N88: ProductAttributes | O88: ATTRIBUTE TYPE: Assay | P88: 0 | Q88: 665118 | R88: 0.97 | S88: Y | T88: Purity | U88: 0 | V88: 0
A89: organometallics | D89: culture media | E89: dehydrated culture media | H89: amino acids(no product type) | I89: amino acids | J89: 0 | K89: functional group | L89: High priority attribute | M89: Priority 2 | N89: ProductAttributes | O89: ATTRIBUTE TYPE: Functional group | P89: 0 | Q89: 564109 | R89: amine | S89: Y | T89: Functional Group | U89: 0 | V89: 0
A90: oxides and ceramics | D90: culture media | E90: media supplements | H90: amino acids(no product type) | I90: amino acids | J90: 0 | K90: storage temp. | L90: High priority attribute | M90: Priority 2 | N90: ProductAttributes | O90: ATTRIBUTE TYPE: Storage Temp | P90: 0 | Q90: 12805 | R90: 2-8°C | S90: N | T90: 0 | U90: 0 | V90: 0
A91: passive air sample collectors | D91: culture media | E91: microbial culture media | H91: amino acids(no product type) | I91: amino acids | J91: 0 | K91: technique(s) | L91: High priority attribute | M91: Priority 2 | N91: ProductAttributes | O91: ATTRIBUTE TYPE: Titertest | P91: use the drop down in "METHOD" | Q91: 0 | R91: 0 | S91: Y | T91: Technique | U91: method | V91: method
A92: pegs and peos | D92: culture media | E92: ready to use liquids | H92: amino acids(no product type) | I92: amino acids | J92: 0 | K92: cation traces | L92: Low priority attribute | M92: Priority 3 | N92: ProductAttributes | O92: ATTRIBUTE TYPE: Cation Traces | P92: 0 | Q92: 561505 | R92: Se: ≥39.5%; heavy metals: ≤10 ppm | S92: N | T92: 0 | U92: 0 | V92: 0
A93: photometry kits and reagents | D93: culture media | E93: ready to use plates | H93: amino acids(no product type) | I93: amino acids | J93: 0 | K93: color | L93: Low priority attribute | M93: Priority 3 | N93: ProductAttributes | O93: ATTRIBUTE TYPE: Color | P93: 0 | Q93: 561505 | R93: white to off-white | S93: Y | T93: Color | U93: 0 | V93: 0
A94: pipette tips | D94: culture media | E94: (no product type) | H94: amino acids(no product type) | I94: amino acids | J94: 0 | K94: impurities | L94: Low priority attribute | M94: Priority 3 | N94: ProductAttributes | O94: ATTRIBUTE TYPE: Impurities | P94: 0 | Q94: 690589 | R94: ≤0.2% water | S94: N | T94: 0 | U94: 0 | V94: 0
A95: pipettes | D95: cylinder | E95: cloning | H95: amino acids(no product type) | I95: amino acids | J95: 0 | K95: InChI | L95: Low priority attribute | M95: Priority 3 | N95: Aliases | O95: drop down type: InChl | P95: must be on the substance level | Q95: 665118 | R95: 1S/C8H9NO3/c1-12-5-2-3-7(9)6(4-5)8(10)11/h2-4H,9H2,1H3,(H,10,11) | S95: N | T95: 0 | U95: 0 | V95: 0
A96: pipettors | D96: cylinder | E96: volumetric | H96: amino acids(no product type) | I96: amino acids | J96: 0 | K96: InChI key | L96: Low priority attribute | M96: Priority 3 | N96: Aliases | O96: drop down type: InChl key | P96: must be on the substance level | Q96: 665118 | R96: UMKSAURFQFUULT-UHFFFAOYSA-N | S96: N | T96: 0 | U96: 0 | V96: 0
A97: plasmid vectors | D97: detergents | E97: (no product type) | H97: amino acids(no product type) | I97: amino acids | J97: 0 | K97: mp | L97: Low priority attribute | M97: Priority 3 | N97: ProductAttributes | O97: ATTRIBUTE TYPE: Melting Point | P97: 0 | Q97: 665118 | R97: 148-152 °C | S97: Y | T97: mp | U97: ? | V97: 0
A98: plates | D98: dishes | E98: crucible | H98: amino acids(no product type) | I98: amino acids | J98: 0 | K98: optical activity | L98: Low priority attribute | M98: Priority 3 | N98: ProductAttributes | O98: ATTRIBUTE TYPE: Optical Activity | P98: 0 | Q98: 670871 | R98: [α]/D 20.0±2.0°, c = 2 in H2O | S98: N | T98: 0 | U98: 0 | V98: 0
A99: polymerization tools | D99: dishes | E99: crystalizing or evaporating or combustion | H99: amino acids(no product type) | I99: amino acids | J99: 0 | K99: product line | L99: Low priority attribute | M99: Priority 3 | N99: ProductAttributes | O99: ATTRIBUTE TYPE: Product Line | P99: 0 | Q99: 8.52383 | R99: Novabiochem® | S99: Y | T99: product line | U99: 0 | V99: 0
A100: precast gels | D100: dishes | E100: culture or petri | H100: amino acids(no product type) | I100: amino acids | J100: 0 | K100: SMILES string | L100: Low priority attribute | M100: Priority 3 | N100: Aliases | O100: drop down type: SMILES | P100: must be on the substance level; 30 characters or less; if more than 30 characters, raise a JIRA for CorpBase Helpdesk | Q100: 665118 | R100: COc1ccc(N)c(c1)C(O)=O | S100: N | T100: 0 | U100: 0 | V100: 0
...
